{"sysstat": {
	"hosts": [
		{
			"nodename": "lbnl-dtn2.testbed100.es.net",
			"sysname": "Linux",
			"release": "6.11.0-rc4-bbr3-skb45",
			"machine": "x86_64",
			"number-of-cpus": 32,
			"date": "09/09/2024",
			"statistics": [
				{
					"timestamp": "08:50:10 PM",
					"cpu-load": [
						{"cpu": "0", "usr": 0.50, "nice": 0.00, "sys": 0.00, "iowait": 0.00, "irq": 0.00, "soft": 0.00, "steal": 0.00, "guest": 0.00, "gnice": 0.00, "idle": 99.50},
						{"cpu": "1", "usr": 0.00, "nice": 0.00, "sys": 0.00, "iowait": 0.00, "irq": 0.00, "soft": 0.00, "steal": 0.00, "guest": 0.00, "gnice": 0.00, "idle": 100.00},
						{"cpu": "2", "usr": 0.00, "nice": 0.00, "sys": 0.00, "iowait": 0.00, "irq": 0.00, "soft": 0.00, "steal": 0.00, "guest": 0.00, "gnice": 0.00, "idle": 100.00},
						{"cpu": "3", "usr": 0.00, "nice": 0.00, "sys": 0.00, "iowait": 0.00, "irq": 0.00, "soft": 0.00, "steal": 0.00, "guest": 0.00, "gnice": 0.00, "idle": 100.00},
						{"cpu": "4", "usr": 0.00, "nice": 0.00, "sys": 0.00, "iowait": 0.00, "irq": 0.00, "soft": 0.00, "steal": 0.00, "guest": 0.00, "gnice": 0.00, "idle": 100.00},
						{"cpu": "5", "usr": 0.00, "nice": 0.00, "sys": 0.00, "iowait": 0.00, "irq": 0.00, "soft": 0.00, "steal": 0.00, "guest": 0.00, "gnice": 0.00, "idle": 100.00},
						{"cpu": "6", "usr": 0.00, "nice": 0.00, "sys": 0.00, "iowait": 0.00, "irq": 0.00, "soft": 0.00, "steal": 0.00, "guest": 0.00, "gnice": 0.00, "idle": 100.00},
						{"cpu": "7", "usr": 0.00, "nice": 0.00, "sys": 0.00, "iowait": 0.00, "irq": 0.00, "soft": 0.00, "steal": 0.00, "guest": 0.00, "gnice": 0.00, "idle": 100.00},
						{"cpu": "8", "usr": 0.00, "nice": 0.00, "sys": 0.00, "iowait": 0.00, "irq": 0.00, "soft": 0.00, "steal": 0.00, "guest": 0.00, "gnice": 0.00, "idle": 100.00},
						{"cpu": "9", "usr": 0.00, "nice": 0.00, "sys": 0.00, "iowait": 0.00, "irq": 0.00, "soft": 0.00, "steal": 0.00, "guest": 0.00, "gnice": 0.00, "idle": 100.00},
						{"cpu": "10", "usr": 0.00, "nice": 0.00, "sys": 0.00, "iowait": 0.00, "irq": 0.00, "soft": 0.00, "steal": 0.00, "guest": 0.00, "gnice": 0.00, "idle": 100.00},
						{"cpu": "11", "usr": 0.00, "nice": 0.00, "sys": 0.00, "iowait": 0.00, "irq": 0.00, "soft": 0.00, "steal": 0.00, "guest": 0.00, "gnice": 0.00, "idle": 100.00},
						{"cpu": "12", "usr": 0.00, "nice": 0.00, "sys": 0.00, "iowait": 0.00, "irq": 0.00, "soft": 0.00, "steal": 0.00, "guest": 0.00, "gnice": 0.00, "idle": 100.00},
						{"cpu": "13", "usr": 0.00, "nice": 0.00, "sys": 0.00, "iowait": 0.00, "irq": 0.00, "soft": 0.00, "steal": 0.00, "guest": 0.00, "gnice": 0.00, "idle": 100.00},
						{"cpu": "14", "usr": 0.00, "nice": 0.00, "sys": 0.00, "iowait": 0.00, "irq": 0.00, "soft": 0.00, "steal": 0.00, "guest": 0.00, "gnice": 0.00, "idle": 100.00},
						{"cpu": "15", "usr": 0.00, "nice": 0.00, "sys": 0.00, "iowait": 0.00, "irq": 0.00, "soft": 0.00, "steal": 0.00, "guest": 0.00, "gnice": 0.00, "idle": 100.00}
					]
				},
				{
					"timestamp": "08:50:12 PM",
					"cpu-load": [
						{"cpu": "0", "usr": 0.00, "nice": 0.00, "sys": 0.00, "iowait": 0.00, "irq": 0.00, "soft": 0.00, "steal": 0.00, "guest": 0.00, "gnice": 0.00, "idle": 100.00},
						{"cpu": "1", "usr": 0.00, "nice": 0.00, "sys": 0.00, "iowait": 0.00, "irq": 0.00, "soft": 0.00, "steal": 0.00, "guest": 0.00, "gnice": 0.00, "idle": 100.00},
						{"cpu": "2", "usr": 0.00, "nice": 0.00, "sys": 0.00, "iowait": 0.00, "irq": 0.00, "soft": 0.00, "steal": 0.00, "guest": 0.00, "gnice": 0.00, "idle": 100.00},
						{"cpu": "3", "usr": 0.00, "nice": 0.00, "sys": 0.00, "iowait": 0.00, "irq": 0.00, "soft": 0.00, "steal": 0.00, "guest": 0.00, "gnice": 0.00, "idle": 100.00},
						{"cpu": "4", "usr": 0.00, "nice": 0.00, "sys": 0.00, "iowait": 0.00, "irq": 0.00, "soft": 0.00, "steal": 0.00, "guest": 0.00, "gnice": 0.00, "idle": 100.00},
						{"cpu": "5", "usr": 0.00, "nice": 0.00, "sys": 0.00, "iowait": 0.00, "irq": 0.00, "soft": 0.00, "steal": 0.00, "guest": 0.00, "gnice": 0.00, "idle": 100.00},
						{"cpu": "6", "usr": 0.00, "nice": 0.00, "sys": 0.00, "iowait": 0.00, "irq": 0.00, "soft": 0.00, "steal": 0.00, "guest": 0.00, "gnice": 0.00, "idle": 100.00},
						{"cpu": "7", "usr": 0.00, "nice": 0.00, "sys": 0.00, "iowait": 0.00, "irq": 0.00, "soft": 0.00, "steal": 0.00, "guest": 0.00, "gnice": 0.00, "idle": 100.00},
						{"cpu": "8", "usr": 0.00, "nice": 0.00, "sys": 0.00, "iowait": 0.00, "irq": 0.00, "soft": 0.00, "steal": 0.00, "guest": 0.00, "gnice": 0.00, "idle": 100.00},
						{"cpu": "9", "usr": 0.00, "nice": 0.00, "sys": 0.00, "iowait": 0.00, "irq": 0.00, "soft": 0.00, "steal": 0.00, "guest": 0.00, "gnice": 0.00, "idle": 100.00},
						{"cpu": "10", "usr": 0.00, "nice": 0.00, "sys": 0.00, "iowait": 0.00, "irq": 0.00, "soft": 0.00, "steal": 0.00, "guest": 0.00, "gnice": 0.00, "idle": 100.00},
						{"cpu": "11", "usr": 0.00, "nice": 0.00, "sys": 0.00, "iowait": 0.00, "irq": 0.00, "soft": 0.00, "steal": 0.00, "guest": 0.00, "gnice": 0.00, "idle": 100.00},
						{"cpu": "12", "usr": 0.00, "nice": 0.00, "sys": 0.00, "iowait": 0.00, "irq": 0.00, "soft": 0.00, "steal": 0.00, "guest": 0.00, "gnice": 0.00, "idle": 100.00},
						{"cpu": "13", "usr": 0.00, "nice": 0.00, "sys": 0.00, "iowait": 0.00, "irq": 0.00, "soft": 0.00, "steal": 0.00, "guest": 0.00, "gnice": 0.00, "idle": 100.00},
						{"cpu": "14", "usr": 0.00, "nice": 0.00, "sys": 0.00, "iowait": 0.00, "irq": 0.00, "soft": 0.00, "steal": 0.00, "guest": 0.00, "gnice": 0.00, "idle": 100.00},
						{"cpu": "15", "usr": 0.00, "nice": 0.00, "sys": 0.00, "iowait": 0.00, "irq": 0.00, "soft": 0.00, "steal": 0.00, "guest": 0.00, "gnice": 0.00, "idle": 100.00}
					]
				},
				{
					"timestamp": "08:50:14 PM",
					"cpu-load": [
						{"cpu": "0", "usr": 0.00, "nice": 0.00, "sys": 0.00, "iowait": 0.00, "irq": 0.00, "soft": 0.00, "steal": 0.00, "guest": 0.00, "gnice": 0.00, "idle": 100.00},
						{"cpu": "1", "usr": 0.00, "nice": 0.00, "sys": 0.00, "iowait": 0.00, "irq": 0.00, "soft": 0.00, "steal": 0.00, "guest": 0.00, "gnice": 0.00, "idle": 100.00},
						{"cpu": "2", "usr": 0.00, "nice": 0.00, "sys": 0.00, "iowait": 0.00, "irq": 0.00, "soft": 0.00, "steal": 0.00, "guest": 0.00, "gnice": 0.00, "idle": 100.00},
						{"cpu": "3", "usr": 0.00, "nice": 0.00, "sys": 0.00, "iowait": 0.00, "irq": 0.00, "soft": 0.00, "steal": 0.00, "guest": 0.00, "gnice": 0.00, "idle": 100.00},
						{"cpu": "4", "usr": 0.00, "nice": 0.00, "sys": 0.00, "iowait": 0.00, "irq": 0.00, "soft": 0.00, "steal": 0.00, "guest": 0.00, "gnice": 0.00, "idle": 100.00},
						{"cpu": "5", "usr": 0.00, "nice": 0.00, "sys": 0.00, "iowait": 0.00, "irq": 0.00, "soft": 0.00, "steal": 0.00, "guest": 0.00, "gnice": 0.00, "idle": 100.00},
						{"cpu": "6", "usr": 0.00, "nice": 0.00, "sys": 0.00, "iowait": 0.00, "irq": 0.00, "soft": 0.00, "steal": 0.00, "guest": 0.00, "gnice": 0.00, "idle": 100.00},
						{"cpu": "7", "usr": 0.00, "nice": 0.00, "sys": 0.00, "iowait": 0.00, "irq": 0.00, "soft": 0.00, "steal": 0.00, "guest": 0.00, "gnice": 0.00, "idle": 100.00},
						{"cpu": "8", "usr": 0.00, "nice": 0.00, "sys": 0.00, "iowait": 0.00, "irq": 0.00, "soft": 0.00, "steal": 0.00, "guest": 0.00, "gnice": 0.00, "idle": 100.00},
						{"cpu": "9", "usr": 0.00, "nice": 0.00, "sys": 0.00, "iowait": 0.00, "irq": 0.00, "soft": 0.00, "steal": 0.00, "guest": 0.00, "gnice": 0.00, "idle": 100.00},
						{"cpu": "10", "usr": 0.00, "nice": 0.00, "sys": 0.00, "iowait": 0.00, "irq": 0.00, "soft": 0.00, "steal": 0.00, "guest": 0.00, "gnice": 0.00, "idle": 100.00},
						{"cpu": "11", "usr": 0.00, "nice": 0.00, "sys": 0.00, "iowait": 0.00, "irq": 0.00, "soft": 0.00, "steal": 0.00, "guest": 0.00, "gnice": 0.00, "idle": 100.00},
						{"cpu": "12", "usr": 0.00, "nice": 0.00, "sys": 0.00, "iowait": 0.00, "irq": 0.00, "soft": 0.00, "steal": 0.00, "guest": 0.00, "gnice": 0.00, "idle": 100.00},
						{"cpu": "13", "usr": 0.00, "nice": 0.00, "sys": 0.00, "iowait": 0.00, "irq": 0.00, "soft": 0.00, "steal": 0.00, "guest": 0.00, "gnice": 0.00, "idle": 100.00},
						{"cpu": "14", "usr": 0.00, "nice": 0.00, "sys": 0.00, "iowait": 0.00, "irq": 0.00, "soft": 0.00, "steal": 0.00, "guest": 0.00, "gnice": 0.00, "idle": 100.00},
						{"cpu": "15", "usr": 0.00, "nice": 0.00, "sys": 0.00, "iowait": 0.00, "irq": 0.00, "soft": 0.00, "steal": 0.00, "guest": 0.00, "gnice": 0.00, "idle": 100.00}
					]
				},
				{
					"timestamp": "08:50:16 PM",
					"cpu-load": [
						{"cpu": "0", "usr": 0.00, "nice": 0.00, "sys": 0.67, "iowait": 0.00, "irq": 0.00, "soft": 1.33, "steal": 0.00, "guest": 0.00, "gnice": 0.00, "idle": 98.00},
						{"cpu": "1", "usr": 0.00, "nice": 0.00, "sys": 0.00, "iowait": 0.00, "irq": 0.00, "soft": 0.00, "steal": 0.00, "guest": 0.00, "gnice": 0.00, "idle": 100.00},
						{"cpu": "2", "usr": 0.00, "nice": 0.00, "sys": 0.84, "iowait": 0.00, "irq": 0.00, "soft": 4.20, "steal": 0.00, "guest": 0.00, "gnice": 0.00, "idle": 94.96},
						{"cpu": "3", "usr": 0.00, "nice": 0.00, "sys": 0.00, "iowait": 0.00, "irq": 0.00, "soft": 0.00, "steal": 0.00, "guest": 0.00, "gnice": 0.00, "idle": 100.00},
						{"cpu": "4", "usr": 0.00, "nice": 0.00, "sys": 0.00, "iowait": 0.00, "irq": 0.00, "soft": 1.42, "steal": 0.00, "guest": 0.00, "gnice": 0.00, "idle": 98.58},
						{"cpu": "5", "usr": 0.00, "nice": 0.00, "sys": 0.66, "iowait": 0.00, "irq": 0.00, "soft": 0.66, "steal": 0.00, "guest": 0.00, "gnice": 0.00, "idle": 98.68},
						{"cpu": "6", "usr": 0.00, "nice": 0.00, "sys": 0.00, "iowait": 0.00, "irq": 0.00, "soft": 0.53, "steal": 0.00, "guest": 0.00, "gnice": 0.00, "idle": 99.47},
						{"cpu": "7", "usr": 0.00, "nice": 0.00, "sys": 0.71, "iowait": 0.00, "irq": 0.00, "soft": 2.13, "steal": 0.00, "guest": 0.00, "gnice": 0.00, "idle": 97.16},
						{"cpu": "8", "usr": 0.62, "nice": 0.00, "sys": 20.50, "iowait": 0.00, "irq": 0.00, "soft": 1.24, "steal": 0.00, "guest": 0.00, "gnice": 0.00, "idle": 77.64},
						{"cpu": "9", "usr": 0.00, "nice": 0.00, "sys": 15.98, "iowait": 0.00, "irq": 0.00, "soft": 0.59, "steal": 0.00, "guest": 0.00, "gnice": 0.00, "idle": 83.43},
						{"cpu": "10", "usr": 0.60, "nice": 0.00, "sys": 21.69, "iowait": 0.00, "irq": 0.00, "soft": 1.20, "steal": 0.00, "guest": 0.00, "gnice": 0.00, "idle": 76.51},
						{"cpu": "11", "usr": 0.00, "nice": 0.00, "sys": 19.39, "iowait": 0.00, "irq": 0.00, "soft": 1.21, "steal": 0.00, "guest": 0.00, "gnice": 0.00, "idle": 79.39},
						{"cpu": "12", "usr": 0.60, "nice": 0.00, "sys": 16.27, "iowait": 0.00, "irq": 0.00, "soft": 1.20, "steal": 0.00, "guest": 0.00, "gnice": 0.00, "idle": 81.93},
						{"cpu": "13", "usr": 0.59, "nice": 0.00, "sys": 20.00, "iowait": 0.00, "irq": 0.00, "soft": 1.18, "steal": 0.00, "guest": 0.00, "gnice": 0.00, "idle": 78.24},
						{"cpu": "14", "usr": 0.61, "nice": 0.00, "sys": 21.47, "iowait": 0.00, "irq": 0.00, "soft": 1.23, "steal": 0.00, "guest": 0.00, "gnice": 0.00, "idle": 76.69},
						{"cpu": "15", "usr": 1.20, "nice": 0.00, "sys": 21.69, "iowait": 0.00, "irq": 0.00, "soft": 1.20, "steal": 0.00, "guest": 0.00, "gnice": 0.00, "idle": 75.90}
					]
				},
				{
					"timestamp": "08:50:18 PM",
					"cpu-load": [
						{"cpu": "0", "usr": 0.00, "nice": 0.00, "sys": 0.00, "iowait": 0.00, "irq": 0.00, "soft": 0.68, "steal": 0.00, "guest": 0.00, "gnice": 0.00, "idle": 99.32},
						{"cpu": "1", "usr": 0.00, "nice": 0.00, "sys": 0.65, "iowait": 0.00, "irq": 0.00, "soft": 0.65, "steal": 0.00, "guest": 0.00, "gnice": 0.00, "idle": 98.69},
						{"cpu": "2", "usr": 0.00, "nice": 0.00, "sys": 0.00, "iowait": 0.00, "irq": 0.00, "soft": 3.25, "steal": 0.00, "guest": 0.00, "gnice": 0.00, "idle": 96.75},
						{"cpu": "3", "usr": 0.00, "nice": 0.00, "sys": 0.52, "iowait": 0.00, "irq": 0.00, "soft": 0.52, "steal": 0.00, "guest": 0.00, "gnice": 0.00, "idle": 98.95},
						{"cpu": "4", "usr": 0.00, "nice": 0.00, "sys": 0.71, "iowait": 0.00, "irq": 0.00, "soft": 2.14, "steal": 0.00, "guest": 0.00, "gnice": 0.00, "idle": 97.14},
						{"cpu": "5", "usr": 0.00, "nice": 0.00, "sys": 0.65, "iowait": 0.00, "irq": 0.00, "soft": 1.96, "steal": 0.00, "guest": 0.00, "gnice": 0.00, "idle": 97.39},
						{"cpu": "6", "usr": 0.00, "nice": 0.00, "sys": 0.53, "iowait": 0.00, "irq": 0.00, "soft": 0.00, "steal": 0.00, "guest": 0.00, "gnice": 0.00, "idle": 99.47},
						{"cpu": "7", "usr": 0.00, "nice": 0.00, "sys": 0.73, "iowait": 0.00, "irq": 0.00, "soft": 3.65, "steal": 0.00, "guest": 0.00, "gnice": 0.00, "idle": 95.62},
						{"cpu": "8", "usr": 0.62, "nice": 0.00, "sys": 20.62, "iowait": 0.00, "irq": 0.00, "soft": 1.25, "steal": 0.00, "guest": 0.00, "gnice": 0.00, "idle": 77.50},
						{"cpu": "9", "usr": 0.61, "nice": 0.00, "sys": 22.09, "iowait": 0.00, "irq": 0.00, "soft": 1.84, "steal": 0.00, "guest": 0.00, "gnice": 0.00, "idle": 75.46},
						{"cpu": "10", "usr": 0.57, "nice": 0.00, "sys": 15.52, "iowait": 0.00, "irq": 0.00, "soft": 1.15, "steal": 0.00, "guest": 0.00, "gnice": 0.00, "idle": 82.76},
						{"cpu": "11", "usr": 0.58, "nice": 0.00, "sys": 19.88, "iowait": 0.00, "irq": 0.00, "soft": 1.17, "steal": 0.00, "guest": 0.00, "gnice": 0.00, "idle": 78.36},
						{"cpu": "12", "usr": 0.58, "nice": 0.00, "sys": 19.65, "iowait": 0.00, "irq": 0.00, "soft": 1.16, "steal": 0.00, "guest": 0.00, "gnice": 0.00, "idle": 78.61},
						{"cpu": "13", "usr": 0.60, "nice": 0.00, "sys": 20.24, "iowait": 0.00, "irq": 0.00, "soft": 1.19, "steal": 0.00, "guest": 0.00, "gnice": 0.00, "idle": 77.98},
						{"cpu": "14", "usr": 0.00, "nice": 0.00, "sys": 23.67, "iowait": 0.00, "irq": 0.00, "soft": 1.78, "steal": 0.00, "guest": 0.00, "gnice": 0.00, "idle": 74.56},
						{"cpu": "15", "usr": 0.61, "nice": 0.00, "sys": 22.42, "iowait": 0.00, "irq": 0.00, "soft": 1.21, "steal": 0.00, "guest": 0.00, "gnice": 0.00, "idle": 75.76}
					]
				},
				{
					"timestamp": "08:50:20 PM",
					"cpu-load": [
						{"cpu": "0", "usr": 0.00, "nice": 0.00, "sys": 0.63, "iowait": 0.00, "irq": 0.00, "soft": 1.26, "steal": 0.00, "guest": 0.00, "gnice": 0.00, "idle": 98.11},
						{"cpu": "1", "usr": 0.00, "nice": 0.00, "sys": 0.00, "iowait": 0.00, "irq": 0.00, "soft": 1.30, "steal": 0.00, "guest": 0.00, "gnice": 0.00, "idle": 98.70},
						{"cpu": "2", "usr": 0.00, "nice": 0.00, "sys": 0.78, "iowait": 0.00, "irq": 0.00, "soft": 3.10, "steal": 0.00, "guest": 0.00, "gnice": 0.00, "idle": 96.12},
						{"cpu": "3", "usr": 0.00, "nice": 0.00, "sys": 0.00, "iowait": 0.00, "irq": 0.00, "soft": 0.00, "steal": 0.00, "guest": 0.00, "gnice": 0.00, "idle": 100.00},
						{"cpu": "4", "usr": 0.00, "nice": 0.00, "sys": 0.68, "iowait": 0.00, "irq": 0.00, "soft": 1.37, "steal": 0.00, "guest": 0.00, "gnice": 0.00, "idle": 97.95},
						{"cpu": "5", "usr": 0.00, "nice": 0.00, "sys": 0.00, "iowait": 0.00, "irq": 0.00, "soft": 1.26, "steal": 0.00, "guest": 0.00, "gnice": 0.00, "idle": 98.74},
						{"cpu": "6", "usr": 0.00, "nice": 0.00, "sys": 0.00, "iowait": 0.00, "irq": 0.00, "soft": 0.52, "steal": 0.00, "guest": 0.00, "gnice": 0.00, "idle": 99.48},
						{"cpu": "7", "usr": 0.00, "nice": 0.00, "sys": 0.67, "iowait": 0.00, "irq": 0.00, "soft": 1.34, "steal": 0.00, "guest": 0.00, "gnice": 0.00, "idle": 97.99},
						{"cpu": "8", "usr": 0.00, "nice": 0.00, "sys": 38.69, "iowait": 0.00, "irq": 0.00, "soft": 0.60, "steal": 0.00, "guest": 0.00, "gnice": 0.00, "idle": 60.71},
						{"cpu": "9", "usr": 0.00, "nice": 0.00, "sys": 40.35, "iowait": 0.00, "irq": 0.00, "soft": 0.58, "steal": 0.00, "guest": 0.00, "gnice": 0.00, "idle": 59.06},
						{"cpu": "10", "usr": 0.57, "nice": 0.00, "sys": 36.36, "iowait": 0.00, "irq": 0.00, "soft": 0.57, "steal": 0.00, "guest": 0.00, "gnice": 0.00, "idle": 62.50},
						{"cpu": "11", "usr": 0.58, "nice": 0.00, "sys": 37.43, "iowait": 0.00, "irq": 0.00, "soft": 0.58, "steal": 0.00, "guest": 0.00, "gnice": 0.00, "idle": 61.40},
						{"cpu": "12", "usr": 0.56, "nice": 0.00, "sys": 36.52, "iowait": 0.00, "irq": 0.00, "soft": 1.12, "steal": 0.00, "guest": 0.00, "gnice": 0.00, "idle": 61.80},
						{"cpu": "13", "usr": 0.58, "nice": 0.00, "sys": 37.21, "iowait": 0.00, "irq": 0.00, "soft": 0.00, "steal": 0.00, "guest": 0.00, "gnice": 0.00, "idle": 62.21},
						{"cpu": "14", "usr": 0.60, "nice": 0.00, "sys": 39.29, "iowait": 0.00, "irq": 0.00, "soft": 0.60, "steal": 0.00, "guest": 0.00, "gnice": 0.00, "idle": 59.52},
						{"cpu": "15", "usr": 0.00, "nice": 0.00, "sys": 39.41, "iowait": 0.00, "irq": 0.00, "soft": 1.18, "steal": 0.00, "guest": 0.00, "gnice": 0.00, "idle": 59.41}
					]
				},
				{
					"timestamp": "08:50:22 PM",
					"cpu-load": [
						{"cpu": "0", "usr": 0.00, "nice": 0.00, "sys": 0.00, "iowait": 0.00, "irq": 0.00, "soft": 0.00, "steal": 0.00, "guest": 0.00, "gnice": 0.00, "idle": 100.00},
						{"cpu": "1", "usr": 0.00, "nice": 0.00, "sys": 0.58, "iowait": 0.00, "irq": 0.00, "soft": 0.00, "steal": 0.00, "guest": 0.00, "gnice": 0.00, "idle": 99.42},
						{"cpu": "2", "usr": 0.00, "nice": 0.00, "sys": 0.00, "iowait": 0.00, "irq": 0.00, "soft": 0.64, "steal": 0.00, "guest": 0.00, "gnice": 0.00, "idle": 99.36},
						{"cpu": "3", "usr": 0.00, "nice": 0.00, "sys": 0.00, "iowait": 0.00, "irq": 0.00, "soft": 0.00, "steal": 0.00, "guest": 0.00, "gnice": 0.00, "idle": 100.00},
						{"cpu": "4", "usr": 0.00, "nice": 0.00, "sys": 0.00, "iowait": 0.00, "irq": 0.00, "soft": 0.60, "steal": 0.00, "guest": 0.00, "gnice": 0.00, "idle": 99.40},
						{"cpu": "5", "usr": 0.00, "nice": 0.00, "sys": 0.00, "iowait": 0.00, "irq": 0.00, "soft": 0.00, "steal": 0.00, "guest": 0.00, "gnice": 0.00, "idle": 100.00},
						{"cpu": "6", "usr": 0.00, "nice": 0.00, "sys": 0.00, "iowait": 0.00, "irq": 0.00, "soft": 0.00, "steal": 0.00, "guest": 0.00, "gnice": 0.00, "idle": 100.00},
						{"cpu": "7", "usr": 0.00, "nice": 0.00, "sys": 0.00, "iowait": 0.00, "irq": 0.00, "soft": 0.00, "steal": 0.00, "guest": 0.00, "gnice": 0.00, "idle": 100.00},
						{"cpu": "8", "usr": 0.00, "nice": 0.00, "sys": 73.18, "iowait": 0.00, "irq": 0.00, "soft": 0.56, "steal": 0.00, "guest": 0.00, "gnice": 0.00, "idle": 26.26},
						{"cpu": "9", "usr": 0.56, "nice": 0.00, "sys": 73.89, "iowait": 0.00, "irq": 0.00, "soft": 0.00, "steal": 0.00, "guest": 0.00, "gnice": 0.00, "idle": 25.56},
						{"cpu": "10", "usr": 0.00, "nice": 0.00, "sys": 74.73, "iowait": 0.00, "irq": 0.00, "soft": 0.00, "steal": 0.00, "guest": 0.00, "gnice": 0.00, "idle": 25.27},
						{"cpu": "11", "usr": 0.00, "nice": 0.00, "sys": 75.28, "iowait": 0.00, "irq": 0.00, "soft": 0.56, "steal": 0.00, "guest": 0.00, "gnice": 0.00, "idle": 24.16},
						{"cpu": "12", "usr": 0.54, "nice": 0.00, "sys": 73.66, "iowait": 0.00, "irq": 0.00, "soft": 0.54, "steal": 0.00, "guest": 0.00, "gnice": 0.00, "idle": 25.27},
						{"cpu": "13", "usr": 0.00, "nice": 0.00, "sys": 73.51, "iowait": 0.00, "irq": 0.00, "soft": 0.54, "steal": 0.00, "guest": 0.00, "gnice": 0.00, "idle": 25.95},
						{"cpu": "14", "usr": 0.00, "nice": 0.00, "sys": 75.41, "iowait": 0.00, "irq": 0.00, "soft": 0.55, "steal": 0.00, "guest": 0.00, "gnice": 0.00, "idle": 24.04},
						{"cpu": "15", "usr": 0.56, "nice": 0.00, "sys": 73.89, "iowait": 0.00, "irq": 0.00, "soft": 0.00, "steal": 0.00, "guest": 0.00, "gnice": 0.00, "idle": 25.56}
					]
				},
				{
					"timestamp": "08:50:24 PM",
					"cpu-load": [
						{"cpu": "0", "usr": 0.57, "nice": 0.00, "sys": 0.57, "iowait": 0.00, "irq": 0.00, "soft": 0.57, "steal": 0.00, "guest": 0.00, "gnice": 0.00, "idle": 98.29},
						{"cpu": "1", "usr": 0.00, "nice": 0.00, "sys": 0.57, "iowait": 0.00, "irq": 0.00, "soft": 0.57, "steal": 0.00, "guest": 0.00, "gnice": 0.00, "idle": 98.85},
						{"cpu": "2", "usr": 0.00, "nice": 0.00, "sys": 0.00, "iowait": 0.00, "irq": 0.00, "soft": 0.62, "steal": 0.00, "guest": 0.00, "gnice": 0.00, "idle": 99.38},
						{"cpu": "3", "usr": 0.00, "nice": 0.00, "sys": 0.00, "iowait": 0.00, "irq": 0.00, "soft": 0.00, "steal": 0.00, "guest": 0.00, "gnice": 0.00, "idle": 100.00},
						{"cpu": "4", "usr": 0.00, "nice": 0.00, "sys": 0.00, "iowait": 0.00, "irq": 0.00, "soft": 0.00, "steal": 0.00, "guest": 0.00, "gnice": 0.00, "idle": 100.00},
						{"cpu": "5", "usr": 0.00, "nice": 0.00, "sys": 0.00, "iowait": 0.00, "irq": 0.00, "soft": 0.56, "steal": 0.00, "guest": 0.00, "gnice": 0.00, "idle": 99.44},
						{"cpu": "6", "usr": 0.00, "nice": 0.00, "sys": 0.00, "iowait": 0.00, "irq": 0.00, "soft": 0.00, "steal": 0.00, "guest": 0.00, "gnice": 0.00, "idle": 100.00},
						{"cpu": "7", "usr": 0.00, "nice": 0.00, "sys": 0.00, "iowait": 0.00, "irq": 0.00, "soft": 0.56, "steal": 0.00, "guest": 0.00, "gnice": 0.00, "idle": 99.44},
						{"cpu": "8", "usr": 0.54, "nice": 0.00, "sys": 74.73, "iowait": 0.00, "irq": 0.00, "soft": 0.00, "steal": 0.00, "guest": 0.00, "gnice": 0.00, "idle": 24.73},
						{"cpu": "9", "usr": 0.00, "nice": 0.00, "sys": 74.18, "iowait": 0.00, "irq": 0.00, "soft": 0.55, "steal": 0.00, "guest": 0.00, "gnice": 0.00, "idle": 25.27},
						{"cpu": "10", "usr": 0.54, "nice": 0.00, "sys": 75.81, "iowait": 0.00, "irq": 0.00, "soft": 0.00, "steal": 0.00, "guest": 0.00, "gnice": 0.00, "idle": 23.66},
						{"cpu": "11", "usr": 0.53, "nice": 0.00, "sys": 75.94, "iowait": 0.00, "irq": 0.00, "soft": 0.00, "steal": 0.00, "guest": 0.00, "gnice": 0.00, "idle": 23.53},
						{"cpu": "12", "usr": 0.00, "nice": 0.00, "sys": 75.68, "iowait": 0.00, "irq": 0.00, "soft": 0.00, "steal": 0.00, "guest": 0.00, "gnice": 0.00, "idle": 24.32},
						{"cpu": "13", "usr": 0.54, "nice": 0.00, "sys": 74.05, "iowait": 0.00, "irq": 0.00, "soft": 0.00, "steal": 0.00, "guest": 0.00, "gnice": 0.00, "idle": 25.41},
						{"cpu": "14", "usr": 0.54, "nice": 0.00, "sys": 75.54, "iowait": 0.00, "irq": 0.00, "soft": 0.00, "steal": 0.00, "guest": 0.00, "gnice": 0.00, "idle": 23.91},
						{"cpu": "15", "usr": 0.54, "nice": 0.00, "sys": 74.46, "iowait": 0.00, "irq": 0.00, "soft": 0.54, "steal": 0.00, "guest": 0.00, "gnice": 0.00, "idle": 24.46}
					]
				},
				{
					"timestamp": "08:50:26 PM",
					"cpu-load": [
						{"cpu": "0", "usr": 0.00, "nice": 0.00, "sys": 0.00, "iowait": 0.00, "irq": 0.00, "soft": 0.57, "steal": 0.00, "guest": 0.00, "gnice": 0.00, "idle": 99.43},
						{"cpu": "1", "usr": 0.00, "nice": 0.00, "sys": 0.00, "iowait": 0.00, "irq": 0.00, "soft": 0.58, "steal": 0.00, "guest": 0.00, "gnice": 0.00, "idle": 99.42},
						{"cpu": "2", "usr": 0.00, "nice": 0.00, "sys": 0.64, "iowait": 0.00, "irq": 0.00, "soft": 0.00, "steal": 0.00, "guest": 0.00, "gnice": 0.00, "idle": 99.36},
						{"cpu": "3", "usr": 0.00, "nice": 0.00, "sys": 0.52, "iowait": 0.00, "irq": 0.00, "soft": 0.00, "steal": 0.00, "guest": 0.00, "gnice": 0.00, "idle": 99.48},
						{"cpu": "4", "usr": 0.00, "nice": 0.00, "sys": 0.59, "iowait": 0.00, "irq": 0.00, "soft": 0.59, "steal": 0.00, "guest": 0.00, "gnice": 0.00, "idle": 98.82},
						{"cpu": "5", "usr": 0.00, "nice": 0.00, "sys": 0.57, "iowait": 0.00, "irq": 0.00, "soft": 0.00, "steal": 0.00, "guest": 0.00, "gnice": 0.00, "idle": 99.43},
						{"cpu": "6", "usr": 0.00, "nice": 0.00, "sys": 0.00, "iowait": 0.00, "irq": 0.00, "soft": 0.00, "steal": 0.00, "guest": 0.00, "gnice": 0.00, "idle": 100.00},
						{"cpu": "7", "usr": 0.00, "nice": 0.00, "sys": 0.00, "iowait": 0.00, "irq": 0.00, "soft": 0.00, "steal": 0.00, "guest": 0.00, "gnice": 0.00, "idle": 100.00},
						{"cpu": "8", "usr": 0.55, "nice": 0.00, "sys": 72.68, "iowait": 0.00, "irq": 0.00, "soft": 0.55, "steal": 0.00, "guest": 0.00, "gnice": 0.00, "idle": 26.23},
						{"cpu": "9", "usr": 0.54, "nice": 0.00, "sys": 72.83, "iowait": 0.00, "irq": 0.00, "soft": 0.54, "steal": 0.00, "guest": 0.00, "gnice": 0.00, "idle": 26.09},
						{"cpu": "10", "usr": 0.00, "nice": 0.00, "sys": 74.47, "iowait": 0.00, "irq": 0.00, "soft": 0.53, "steal": 0.00, "guest": 0.00, "gnice": 0.00, "idle": 25.00},
						{"cpu": "11", "usr": 0.00, "nice": 0.00, "sys": 75.00, "iowait": 0.00, "irq": 0.00, "soft": 0.56, "steal": 0.00, "guest": 0.00, "gnice": 0.00, "idle": 24.44},
						{"cpu": "12", "usr": 0.54, "nice": 0.00, "sys": 72.97, "iowait": 0.00, "irq": 0.00, "soft": 0.54, "steal": 0.00, "guest": 0.00, "gnice": 0.00, "idle": 25.95},
						{"cpu": "13", "usr": 0.54, "nice": 0.00, "sys": 72.97, "iowait": 0.00, "irq": 0.00, "soft": 0.54, "steal": 0.00, "guest": 0.00, "gnice": 0.00, "idle": 25.95},
						{"cpu": "14", "usr": 0.00, "nice": 0.00, "sys": 75.00, "iowait": 0.00, "irq": 0.00, "soft": 0.54, "steal": 0.00, "guest": 0.00, "gnice": 0.00, "idle": 24.46},
						{"cpu": "15", "usr": 0.53, "nice": 0.00, "sys": 73.80, "iowait": 0.00, "irq": 0.00, "soft": 0.53, "steal": 0.00, "guest": 0.00, "gnice": 0.00, "idle": 25.13}
					]
				},
				{
					"timestamp": "08:50:28 PM",
					"cpu-load": [
						{"cpu": "0", "usr": 0.00, "nice": 0.00, "sys": 0.58, "iowait": 0.00, "irq": 0.00, "soft": 0.58, "steal": 0.00, "guest": 0.00, "gnice": 0.00, "idle": 98.84},
						{"cpu": "1", "usr": 0.00, "nice": 0.00, "sys": 0.00, "iowait": 0.00, "irq": 0.00, "soft": 0.58, "steal": 0.00, "guest": 0.00, "gnice": 0.00, "idle": 99.42},
						{"cpu": "2", "usr": 0.00, "nice": 0.00, "sys": 0.62, "iowait": 0.00, "irq": 0.00, "soft": 1.25, "steal": 0.00, "guest": 0.00, "gnice": 0.00, "idle": 98.12},
						{"cpu": "3", "usr": 0.00, "nice": 0.00, "sys": 0.00, "iowait": 0.00, "irq": 0.00, "soft": 0.00, "steal": 0.00, "guest": 0.00, "gnice": 0.00, "idle": 100.00},
						{"cpu": "4", "usr": 0.00, "nice": 0.00, "sys": 0.00, "iowait": 0.00, "irq": 0.00, "soft": 0.59, "steal": 0.00, "guest": 0.00, "gnice": 0.00, "idle": 99.41},
						{"cpu": "5", "usr": 0.00, "nice": 0.00, "sys": 0.00, "iowait": 0.00, "irq": 0.00, "soft": 0.57, "steal": 0.00, "guest": 0.00, "gnice": 0.00, "idle": 99.43},
						{"cpu": "6", "usr": 0.00, "nice": 0.00, "sys": 0.00, "iowait": 0.00, "irq": 0.00, "soft": 0.00, "steal": 0.00, "guest": 0.00, "gnice": 0.00, "idle": 100.00},
						{"cpu": "7", "usr": 0.00, "nice": 0.00, "sys": 0.57, "iowait": 0.00, "irq": 0.00, "soft": 0.57, "steal": 0.00, "guest": 0.00, "gnice": 0.00, "idle": 98.86},
						{"cpu": "8", "usr": 0.56, "nice": 0.00, "sys": 74.44, "iowait": 0.00, "irq": 0.00, "soft": 0.00, "steal": 0.00, "guest": 0.00, "gnice": 0.00, "idle": 25.00},
						{"cpu": "9", "usr": 0.55, "nice": 0.00, "sys": 74.59, "iowait": 0.00, "irq": 0.00, "soft": 0.00, "steal": 0.00, "guest": 0.00, "gnice": 0.00, "idle": 24.86},
						{"cpu": "10", "usr": 0.55, "nice": 0.00, "sys": 75.41, "iowait": 0.00, "irq": 0.00, "soft": 0.00, "steal": 0.00, "guest": 0.00, "gnice": 0.00, "idle": 24.04},
						{"cpu": "11", "usr": 0.55, "nice": 0.00, "sys": 75.82, "iowait": 0.00, "irq": 0.00, "soft": 0.00, "steal": 0.00, "guest": 0.00, "gnice": 0.00, "idle": 23.63},
						{"cpu": "12", "usr": 1.09, "nice": 0.00, "sys": 74.32, "iowait": 0.00, "irq": 0.00, "soft": 0.55, "steal": 0.00, "guest": 0.00, "gnice": 0.00, "idle": 24.04},
						{"cpu": "13", "usr": 0.00, "nice": 0.00, "sys": 74.59, "iowait": 0.00, "irq": 0.00, "soft": 0.54, "steal": 0.00, "guest": 0.00, "gnice": 0.00, "idle": 24.86},
						{"cpu": "14", "usr": 0.55, "nice": 0.00, "sys": 74.86, "iowait": 0.00, "irq": 0.00, "soft": 0.55, "steal": 0.00, "guest": 0.00, "gnice": 0.00, "idle": 24.04},
						{"cpu": "15", "usr": 0.53, "nice": 0.00, "sys": 74.33, "iowait": 0.00, "irq": 0.00, "soft": 0.53, "steal": 0.00, "guest": 0.00, "gnice": 0.00, "idle": 24.60}
					]
				},
				{
					"timestamp": "08:50:30 PM",
					"cpu-load": [
						{"cpu": "0", "usr": 0.00, "nice": 0.00, "sys": 0.00, "iowait": 0.00, "irq": 0.00, "soft": 0.00, "steal": 0.00, "guest": 0.00, "gnice": 0.00, "idle": 100.00},
						{"cpu": "1", "usr": 0.00, "nice": 0.00, "sys": 0.57, "iowait": 0.00, "irq": 0.00, "soft": 0.57, "steal": 0.00, "guest": 0.00, "gnice": 0.00, "idle": 98.86},
						{"cpu": "2", "usr": 0.00, "nice": 0.00, "sys": 0.00, "iowait": 0.00, "irq": 0.00, "soft": 0.63, "steal": 0.00, "guest": 0.00, "gnice": 0.00, "idle": 99.37},
						{"cpu": "3", "usr": 0.00, "nice": 0.00, "sys": 0.00, "iowait": 0.00, "irq": 0.00, "soft": 0.00, "steal": 0.00, "guest": 0.00, "gnice": 0.00, "idle": 100.00},
						{"cpu": "4", "usr": 0.00, "nice": 0.00, "sys": 0.00, "iowait": 0.00, "irq": 0.00, "soft": 0.59, "steal": 0.00, "guest": 0.00, "gnice": 0.00, "idle": 99.41},
						{"cpu": "5", "usr": 0.00, "nice": 0.00, "sys": 0.00, "iowait": 0.00, "irq": 0.00, "soft": 0.00, "steal": 0.00, "guest": 0.00, "gnice": 0.00, "idle": 100.00},
						{"cpu": "6", "usr": 0.00, "nice": 0.00, "sys": 0.00, "iowait": 0.00, "irq": 0.00, "soft": 0.00, "steal": 0.00, "guest": 0.00, "gnice": 0.00, "idle": 100.00},
						{"cpu": "7", "usr": 0.00, "nice": 0.00, "sys": 0.00, "iowait": 0.00, "irq": 0.00, "soft": 0.00, "steal": 0.00, "guest": 0.00, "gnice": 0.00, "idle": 100.00},
						{"cpu": "8", "usr": 0.00, "nice": 0.00, "sys": 75.00, "iowait": 0.00, "irq": 0.00, "soft": 0.00, "steal": 0.00, "guest": 0.00, "gnice": 0.00, "idle": 25.00},
						{"cpu": "9", "usr": 0.55, "nice": 0.00, "sys": 75.14, "iowait": 0.00, "irq": 0.00, "soft": 0.00, "steal": 0.00, "guest": 0.00, "gnice": 0.00, "idle": 24.31},
						{"cpu": "10", "usr": 0.54, "nice": 0.00, "sys": 75.00, "iowait": 0.00, "irq": 0.00, "soft": 0.54, "steal": 0.00, "guest": 0.00, "gnice": 0.00, "idle": 23.91},
						{"cpu": "11", "usr": 0.54, "nice": 0.00, "sys": 75.81, "iowait": 0.00, "irq": 0.00, "soft": 0.54, "steal": 0.00, "guest": 0.00, "gnice": 0.00, "idle": 23.12},
						{"cpu": "12", "usr": 0.00, "nice": 0.00, "sys": 74.46, "iowait": 0.00, "irq": 0.00, "soft": 1.09, "steal": 0.00, "guest": 0.00, "gnice": 0.00, "idle": 24.46},
						{"cpu": "13", "usr": 0.55, "nice": 0.00, "sys": 74.73, "iowait": 0.00, "irq": 0.00, "soft": 0.00, "steal": 0.00, "guest": 0.00, "gnice": 0.00, "idle": 24.73},
						{"cpu": "14", "usr": 0.54, "nice": 0.00, "sys": 75.54, "iowait": 0.00, "irq": 0.00, "soft": 0.54, "steal": 0.00, "guest": 0.00, "gnice": 0.00, "idle": 23.37},
						{"cpu": "15", "usr": 0.55, "nice": 0.00, "sys": 74.59, "iowait": 0.00, "irq": 0.00, "soft": 0.00, "steal": 0.00, "guest": 0.00, "gnice": 0.00, "idle": 24.86}
					]
				},
				{
					"timestamp": "08:50:32 PM",
					"cpu-load": [
						{"cpu": "0", "usr": 0.00, "nice": 0.00, "sys": 0.00, "iowait": 0.00, "irq": 0.00, "soft": 0.57, "steal": 0.00, "guest": 0.00, "gnice": 0.00, "idle": 99.43},
						{"cpu": "1", "usr": 0.00, "nice": 0.00, "sys": 0.00, "iowait": 0.00, "irq": 0.00, "soft": 0.00, "steal": 0.00, "guest": 0.00, "gnice": 0.00, "idle": 100.00},
						{"cpu": "2", "usr": 0.00, "nice": 0.00, "sys": 0.00, "iowait": 0.00, "irq": 0.00, "soft": 0.62, "steal": 0.00, "guest": 0.00, "gnice": 0.00, "idle": 99.38},
						{"cpu": "3", "usr": 0.00, "nice": 0.00, "sys": 0.00, "iowait": 0.00, "irq": 0.00, "soft": 0.00, "steal": 0.00, "guest": 0.00, "gnice": 0.00, "idle": 100.00},
						{"cpu": "4", "usr": 0.00, "nice": 0.00, "sys": 0.00, "iowait": 0.00, "irq": 0.00, "soft": 0.00, "steal": 0.00, "guest": 0.00, "gnice": 0.00, "idle": 100.00},
						{"cpu": "5", "usr": 0.00, "nice": 0.00, "sys": 0.00, "iowait": 0.00, "irq": 0.00, "soft": 0.57, "steal": 0.00, "guest": 0.00, "gnice": 0.00, "idle": 99.43},
						{"cpu": "6", "usr": 0.00, "nice": 0.00, "sys": 0.00, "iowait": 0.00, "irq": 0.00, "soft": 0.00, "steal": 0.00, "guest": 0.00, "gnice": 0.00, "idle": 100.00},
						{"cpu": "7", "usr": 0.00, "nice": 0.00, "sys": 0.00, "iowait": 0.00, "irq": 0.00, "soft": 0.57, "steal": 0.00, "guest": 0.00, "gnice": 0.00, "idle": 99.43},
						{"cpu": "8", "usr": 0.54, "nice": 0.00, "sys": 74.46, "iowait": 0.00, "irq": 0.00, "soft": 0.54, "steal": 0.00, "guest": 0.00, "gnice": 0.00, "idle": 24.46},
						{"cpu": "9", "usr": 0.00, "nice": 0.00, "sys": 76.34, "iowait": 0.00, "irq": 0.00, "soft": 0.54, "steal": 0.00, "guest": 0.00, "gnice": 0.00, "idle": 23.12},
						{"cpu": "10", "usr": 0.00, "nice": 0.00, "sys": 76.76, "iowait": 0.00, "irq": 0.00, "soft": 0.00, "steal": 0.00, "guest": 0.00, "gnice": 0.00, "idle": 23.24},
						{"cpu": "11", "usr": 0.53, "nice": 0.00, "sys": 76.19, "iowait": 0.00, "irq": 0.00, "soft": 0.53, "steal": 0.00, "guest": 0.00, "gnice": 0.00, "idle": 22.75},
						{"cpu": "12", "usr": 0.00, "nice": 0.00, "sys": 74.18, "iowait": 0.00, "irq": 0.00, "soft": 0.55, "steal": 0.00, "guest": 0.00, "gnice": 0.00, "idle": 25.27},
						{"cpu": "13", "usr": 0.00, "nice": 0.00, "sys": 74.44, "iowait": 0.00, "irq": 0.00, "soft": 0.00, "steal": 0.00, "guest": 0.00, "gnice": 0.00, "idle": 25.56},
						{"cpu": "14", "usr": 0.00, "nice": 0.00, "sys": 76.11, "iowait": 0.00, "irq": 0.00, "soft": 0.00, "steal": 0.00, "guest": 0.00, "gnice": 0.00, "idle": 23.89},
						{"cpu": "15", "usr": 0.00, "nice": 0.00, "sys": 74.59, "iowait": 0.00, "irq": 0.00, "soft": 0.54, "steal": 0.00, "guest": 0.00, "gnice": 0.00, "idle": 24.86}
					]
				},
				{
					"timestamp": "08:50:34 PM",
					"cpu-load": [
						{"cpu": "0", "usr": 0.00, "nice": 0.00, "sys": 0.00, "iowait": 0.00, "irq": 0.00, "soft": 0.00, "steal": 0.00, "guest": 0.00, "gnice": 0.00, "idle": 100.00},
						{"cpu": "1", "usr": 0.00, "nice": 0.00, "sys": 0.00, "iowait": 0.00, "irq": 0.00, "soft": 0.58, "steal": 0.00, "guest": 0.00, "gnice": 0.00, "idle": 99.42},
						{"cpu": "2", "usr": 0.00, "nice": 0.00, "sys": 0.00, "iowait": 0.00, "irq": 0.00, "soft": 0.00, "steal": 0.00, "guest": 0.00, "gnice": 0.00, "idle": 100.00},
						{"cpu": "3", "usr": 0.00, "nice": 0.00, "sys": 0.00, "iowait": 0.00, "irq": 0.00, "soft": 0.00, "steal": 0.00, "guest": 0.00, "gnice": 0.00, "idle": 100.00},
						{"cpu": "4", "usr": 0.00, "nice": 0.00, "sys": 0.00, "iowait": 0.00, "irq": 0.00, "soft": 0.59, "steal": 0.00, "guest": 0.00, "gnice": 0.00, "idle": 99.41},
						{"cpu": "5", "usr": 0.00, "nice": 0.00, "sys": 0.00, "iowait": 0.00, "irq": 0.00, "soft": 0.00, "steal": 0.00, "guest": 0.00, "gnice": 0.00, "idle": 100.00},
						{"cpu": "6", "usr": 0.00, "nice": 0.00, "sys": 0.00, "iowait": 0.00, "irq": 0.00, "soft": 0.00, "steal": 0.00, "guest": 0.00, "gnice": 0.00, "idle": 100.00},
						{"cpu": "7", "usr": 0.00, "nice": 0.00, "sys": 0.57, "iowait": 0.00, "irq": 0.00, "soft": 0.00, "steal": 0.00, "guest": 0.00, "gnice": 0.00, "idle": 99.43},
						{"cpu": "8", "usr": 0.55, "nice": 0.00, "sys": 74.32, "iowait": 0.00, "irq": 0.00, "soft": 0.00, "steal": 0.00, "guest": 0.00, "gnice": 0.00, "idle": 25.14},
						{"cpu": "9", "usr": 0.00, "nice": 0.00, "sys": 76.76, "iowait": 0.00, "irq": 0.00, "soft": 0.00, "steal": 0.00, "guest": 0.00, "gnice": 0.00, "idle": 23.24},
						{"cpu": "10", "usr": 0.00, "nice": 0.00, "sys": 76.50, "iowait": 0.00, "irq": 0.00, "soft": 0.00, "steal": 0.00, "guest": 0.00, "gnice": 0.00, "idle": 23.50},
						{"cpu": "11", "usr": 0.56, "nice": 0.00, "sys": 75.42, "iowait": 0.00, "irq": 0.00, "soft": 0.00, "steal": 0.00, "guest": 0.00, "gnice": 0.00, "idle": 24.02},
						{"cpu": "12", "usr": 0.53, "nice": 0.00, "sys": 74.07, "iowait": 0.00, "irq": 0.00, "soft": 0.53, "steal": 0.00, "guest": 0.00, "gnice": 0.00, "idle": 24.87},
						{"cpu": "13", "usr": 0.00, "nice": 0.00, "sys": 74.18, "iowait": 0.00, "irq": 0.00, "soft": 0.55, "steal": 0.00, "guest": 0.00, "gnice": 0.00, "idle": 25.27},
						{"cpu": "14", "usr": 0.54, "nice": 0.00, "sys": 75.27, "iowait": 0.00, "irq": 0.00, "soft": 0.54, "steal": 0.00, "guest": 0.00, "gnice": 0.00, "idle": 23.66},
						{"cpu": "15", "usr": 0.54, "nice": 0.00, "sys": 75.14, "iowait": 0.00, "irq": 0.00, "soft": 0.00, "steal": 0.00, "guest": 0.00, "gnice": 0.00, "idle": 24.32}
					]
				},
				{
					"timestamp": "08:50:36 PM",
					"cpu-load": [
						{"cpu": "0", "usr": 0.00, "nice": 0.00, "sys": 0.58, "iowait": 0.00, "irq": 0.00, "soft": 0.58, "steal": 0.00, "guest": 0.00, "gnice": 0.00, "idle": 98.84},
						{"cpu": "1", "usr": 0.00, "nice": 0.00, "sys": 0.58, "iowait": 0.00, "irq": 0.00, "soft": 0.00, "steal": 0.00, "guest": 0.00, "gnice": 0.00, "idle": 99.42},
						{"cpu": "2", "usr": 0.00, "nice": 0.00, "sys": 0.63, "iowait": 0.00, "irq": 0.00, "soft": 0.63, "steal": 0.00, "guest": 0.00, "gnice": 0.00, "idle": 98.74},
						{"cpu": "3", "usr": 0.00, "nice": 0.00, "sys": 0.00, "iowait": 0.00, "irq": 0.00, "soft": 0.00, "steal": 0.00, "guest": 0.00, "gnice": 0.00, "idle": 100.00},
						{"cpu": "4", "usr": 0.00, "nice": 0.00, "sys": 0.00, "iowait": 0.00, "irq": 0.00, "soft": 0.00, "steal": 0.00, "guest": 0.00, "gnice": 0.00, "idle": 100.00},
						{"cpu": "5", "usr": 0.00, "nice": 0.00, "sys": 0.00, "iowait": 0.00, "irq": 0.00, "soft": 0.56, "steal": 0.00, "guest": 0.00, "gnice": 0.00, "idle": 99.44},
						{"cpu": "6", "usr": 0.00, "nice": 0.00, "sys": 0.00, "iowait": 0.00, "irq": 0.00, "soft": 0.00, "steal": 0.00, "guest": 0.00, "gnice": 0.00, "idle": 100.00},
						{"cpu": "7", "usr": 0.00, "nice": 0.00, "sys": 0.00, "iowait": 0.00, "irq": 0.00, "soft": 0.56, "steal": 0.00, "guest": 0.00, "gnice": 0.00, "idle": 99.44},
						{"cpu": "8", "usr": 0.00, "nice": 0.00, "sys": 75.68, "iowait": 0.00, "irq": 0.00, "soft": 0.54, "steal": 0.00, "guest": 0.00, "gnice": 0.00, "idle": 23.78},
						{"cpu": "9", "usr": 0.53, "nice": 0.00, "sys": 77.01, "iowait": 0.00, "irq": 0.00, "soft": 0.00, "steal": 0.00, "guest": 0.00, "gnice": 0.00, "idle": 22.46},
						{"cpu": "10", "usr": 0.53, "nice": 0.00, "sys": 76.19, "iowait": 0.00, "irq": 0.00, "soft": 0.53, "steal": 0.00, "guest": 0.00, "gnice": 0.00, "idle": 22.75},
						{"cpu": "11", "usr": 0.00, "nice": 0.00, "sys": 76.50, "iowait": 0.00, "irq": 0.00, "soft": 0.00, "steal": 0.00, "guest": 0.00, "gnice": 0.00, "idle": 23.50},
						{"cpu": "12", "usr": 0.00, "nice": 0.00, "sys": 74.46, "iowait": 0.00, "irq": 0.00, "soft": 0.54, "steal": 0.00, "guest": 0.00, "gnice": 0.00, "idle": 25.00},
						{"cpu": "13", "usr": 0.55, "nice": 0.00, "sys": 74.32, "iowait": 0.00, "irq": 0.00, "soft": 0.55, "steal": 0.00, "guest": 0.00, "gnice": 0.00, "idle": 24.59},
						{"cpu": "14", "usr": 0.53, "nice": 0.00, "sys": 76.06, "iowait": 0.00, "irq": 0.00, "soft": 0.53, "steal": 0.00, "guest": 0.00, "gnice": 0.00, "idle": 22.87},
						{"cpu": "15", "usr": 0.53, "nice": 0.00, "sys": 75.00, "iowait": 0.00, "irq": 0.00, "soft": 0.53, "steal": 0.00, "guest": 0.00, "gnice": 0.00, "idle": 23.94}
					]
				},
				{
					"timestamp": "08:50:38 PM",
					"cpu-load": [
						{"cpu": "0", "usr": 0.00, "nice": 0.00, "sys": 0.00, "iowait": 0.00, "irq": 0.00, "soft": 0.00, "steal": 0.00, "guest": 0.00, "gnice": 0.00, "idle": 100.00},
						{"cpu": "1", "usr": 0.00, "nice": 0.00, "sys": 0.00, "iowait": 0.00, "irq": 0.00, "soft": 0.58, "steal": 0.00, "guest": 0.00, "gnice": 0.00, "idle": 99.42},
						{"cpu": "2", "usr": 0.00, "nice": 0.00, "sys": 0.63, "iowait": 0.00, "irq": 0.00, "soft": 0.63, "steal": 0.00, "guest": 0.00, "gnice": 0.00, "idle": 98.74},
						{"cpu": "3", "usr": 0.00, "nice": 0.00, "sys": 0.52, "iowait": 0.00, "irq": 0.00, "soft": 0.00, "steal": 0.00, "guest": 0.00, "gnice": 0.00, "idle": 99.48},
						{"cpu": "4", "usr": 0.00, "nice": 0.00, "sys": 0.00, "iowait": 0.00, "irq": 0.00, "soft": 0.58, "steal": 0.00, "guest": 0.00, "gnice": 0.00, "idle": 99.42},
						{"cpu": "5", "usr": 0.00, "nice": 0.00, "sys": 0.57, "iowait": 0.00, "irq": 0.00, "soft": 0.00, "steal": 0.00, "guest": 0.00, "gnice": 0.00, "idle": 99.43},
						{"cpu": "6", "usr": 0.00, "nice": 0.00, "sys": 0.00, "iowait": 0.00, "irq": 0.00, "soft": 0.00, "steal": 0.00, "guest": 0.00, "gnice": 0.00, "idle": 100.00},
						{"cpu": "7", "usr": 0.00, "nice": 0.00, "sys": 0.00, "iowait": 0.00, "irq": 0.00, "soft": 0.00, "steal": 0.00, "guest": 0.00, "gnice": 0.00, "idle": 100.00},
						{"cpu": "8", "usr": 0.55, "nice": 0.00, "sys": 74.03, "iowait": 0.00, "irq": 0.00, "soft": 0.55, "steal": 0.00, "guest": 0.00, "gnice": 0.00, "idle": 24.86},
						{"cpu": "9", "usr": 0.00, "nice": 0.00, "sys": 74.86, "iowait": 0.00, "irq": 0.00, "soft": 0.55, "steal": 0.00, "guest": 0.00, "gnice": 0.00, "idle": 24.59},
						{"cpu": "10", "usr": 0.54, "nice": 0.00, "sys": 75.00, "iowait": 0.00, "irq": 0.00, "soft": 0.00, "steal": 0.00, "guest": 0.00, "gnice": 0.00, "idle": 24.46},
						{"cpu": "11", "usr": 0.55, "nice": 0.00, "sys": 75.82, "iowait": 0.00, "irq": 0.00, "soft": 0.55, "steal": 0.00, "guest": 0.00, "gnice": 0.00, "idle": 23.08},
						{"cpu": "12", "usr": 0.55, "nice": 0.00, "sys": 72.53, "iowait": 0.00, "irq": 0.00, "soft": 1.10, "steal": 0.00, "guest": 0.00, "gnice": 0.00, "idle": 25.82},
						{"cpu": "13", "usr": 0.54, "nice": 0.00, "sys": 74.05, "iowait": 0.00, "irq": 0.00, "soft": 0.54, "steal": 0.00, "guest": 0.00, "gnice": 0.00, "idle": 24.86},
						{"cpu": "14", "usr": 0.00, "nice": 0.00, "sys": 75.81, "iowait": 0.00, "irq": 0.00, "soft": 0.54, "steal": 0.00, "guest": 0.00, "gnice": 0.00, "idle": 23.66},
						{"cpu": "15", "usr": 0.00, "nice": 0.00, "sys": 75.27, "iowait": 0.00, "irq": 0.00, "soft": 0.00, "steal": 0.00, "guest": 0.00, "gnice": 0.00, "idle": 24.73}
					]
				},
				{
					"timestamp": "08:50:40 PM",
					"cpu-load": [
						{"cpu": "0", "usr": 0.00, "nice": 0.00, "sys": 0.00, "iowait": 0.00, "irq": 0.00, "soft": 0.58, "steal": 0.00, "guest": 0.00, "gnice": 0.00, "idle": 99.42},
						{"cpu": "1", "usr": 0.00, "nice": 0.00, "sys": 0.00, "iowait": 0.00, "irq": 0.00, "soft": 0.58, "steal": 0.00, "guest": 0.00, "gnice": 0.00, "idle": 99.42},
						{"cpu": "2", "usr": 0.00, "nice": 0.00, "sys": 0.00, "iowait": 0.00, "irq": 0.00, "soft": 0.63, "steal": 0.00, "guest": 0.00, "gnice": 0.00, "idle": 99.37},
						{"cpu": "3", "usr": 0.00, "nice": 0.00, "sys": 0.00, "iowait": 0.00, "irq": 0.00, "soft": 0.52, "steal": 0.00, "guest": 0.00, "gnice": 0.00, "idle": 99.48},
						{"cpu": "4", "usr": 0.00, "nice": 0.00, "sys": 0.00, "iowait": 0.00, "irq": 0.00, "soft": 0.59, "steal": 0.00, "guest": 0.00, "gnice": 0.00, "idle": 99.41},
						{"cpu": "5", "usr": 0.00, "nice": 0.00, "sys": 0.00, "iowait": 0.00, "irq": 0.00, "soft": 0.00, "steal": 0.00, "guest": 0.00, "gnice": 0.00, "idle": 100.00},
						{"cpu": "6", "usr": 0.00, "nice": 0.00, "sys": 0.00, "iowait": 0.00, "irq": 0.00, "soft": 0.00, "steal": 0.00, "guest": 0.00, "gnice": 0.00, "idle": 100.00},
						{"cpu": "7", "usr": 0.00, "nice": 0.00, "sys": 0.00, "iowait": 0.00, "irq": 0.00, "soft": 0.00, "steal": 0.00, "guest": 0.00, "gnice": 0.00, "idle": 100.00},
						{"cpu": "8", "usr": 0.54, "nice": 0.00, "sys": 75.00, "iowait": 0.00, "irq": 0.00, "soft": 0.00, "steal": 0.00, "guest": 0.00, "gnice": 0.00, "idle": 24.46},
						{"cpu": "9", "usr": 0.54, "nice": 0.00, "sys": 76.34, "iowait": 0.00, "irq": 0.00, "soft": 0.00, "steal": 0.00, "guest": 0.00, "gnice": 0.00, "idle": 23.12},
						{"cpu": "10", "usr": 0.00, "nice": 0.00, "sys": 76.50, "iowait": 0.00, "irq": 0.00, "soft": 0.00, "steal": 0.00, "guest": 0.00, "gnice": 0.00, "idle": 23.50},
						{"cpu": "11", "usr": 0.55, "nice": 0.00, "sys": 74.86, "iowait": 0.00, "irq": 0.00, "soft": 0.55, "steal": 0.00, "guest": 0.00, "gnice": 0.00, "idle": 24.04},
						{"cpu": "12", "usr": 0.55, "nice": 0.00, "sys": 74.18, "iowait": 0.00, "irq": 0.00, "soft": 0.00, "steal": 0.00, "guest": 0.00, "gnice": 0.00, "idle": 25.27},
						{"cpu": "13", "usr": 0.00, "nice": 0.00, "sys": 74.32, "iowait": 0.00, "irq": 0.00, "soft": 0.00, "steal": 0.00, "guest": 0.00, "gnice": 0.00, "idle": 25.68},
						{"cpu": "14", "usr": 0.00, "nice": 0.00, "sys": 76.24, "iowait": 0.00, "irq": 0.00, "soft": 0.00, "steal": 0.00, "guest": 0.00, "gnice": 0.00, "idle": 23.76},
						{"cpu": "15", "usr": 0.54, "nice": 0.00, "sys": 74.73, "iowait": 0.00, "irq": 0.00, "soft": 0.54, "steal": 0.00, "guest": 0.00, "gnice": 0.00, "idle": 24.19}
					]
				},
				{
					"timestamp": "08:50:42 PM",
					"cpu-load": [
						{"cpu": "0", "usr": 0.00, "nice": 0.00, "sys": 0.57, "iowait": 0.00, "irq": 0.00, "soft": 0.57, "steal": 0.00, "guest": 0.00, "gnice": 0.00, "idle": 98.86},
						{"cpu": "1", "usr": 0.00, "nice": 0.00, "sys": 0.00, "iowait": 0.00, "irq": 0.00, "soft": 0.00, "steal": 0.00, "guest": 0.00, "gnice": 0.00, "idle": 100.00},
						{"cpu": "2", "usr": 0.00, "nice": 0.00, "sys": 0.00, "iowait": 0.00, "irq": 0.00, "soft": 0.62, "steal": 0.00, "guest": 0.00, "gnice": 0.00, "idle": 99.38},
						{"cpu": "3", "usr": 0.00, "nice": 0.00, "sys": 0.00, "iowait": 0.00, "irq": 0.00, "soft": 0.00, "steal": 0.00, "guest": 0.00, "gnice": 0.00, "idle": 100.00},
						{"cpu": "4", "usr": 0.00, "nice": 0.00, "sys": 0.00, "iowait": 0.00, "irq": 0.00, "soft": 0.00, "steal": 0.00, "guest": 0.00, "gnice": 0.00, "idle": 100.00},
						{"cpu": "5", "usr": 0.00, "nice": 0.00, "sys": 0.56, "iowait": 0.00, "irq": 0.00, "soft": 0.56, "steal": 0.00, "guest": 0.00, "gnice": 0.00, "idle": 98.88},
						{"cpu": "6", "usr": 0.00, "nice": 0.00, "sys": 0.00, "iowait": 0.00, "irq": 0.00, "soft": 0.52, "steal": 0.00, "guest": 0.00, "gnice": 0.00, "idle": 99.48},
						{"cpu": "7", "usr": 0.00, "nice": 0.00, "sys": 0.00, "iowait": 0.00, "irq": 0.00, "soft": 0.57, "steal": 0.00, "guest": 0.00, "gnice": 0.00, "idle": 99.43},
						{"cpu": "8", "usr": 0.00, "nice": 0.00, "sys": 75.56, "iowait": 0.00, "irq": 0.00, "soft": 0.56, "steal": 0.00, "guest": 0.00, "gnice": 0.00, "idle": 23.89},
						{"cpu": "9", "usr": 0.00, "nice": 0.00, "sys": 75.14, "iowait": 0.00, "irq": 0.00, "soft": 0.54, "steal": 0.00, "guest": 0.00, "gnice": 0.00, "idle": 24.32},
						{"cpu": "10", "usr": 0.54, "nice": 0.00, "sys": 75.81, "iowait": 0.00, "irq": 0.00, "soft": 0.54, "steal": 0.00, "guest": 0.00, "gnice": 0.00, "idle": 23.12},
						{"cpu": "11", "usr": 0.00, "nice": 0.00, "sys": 74.44, "iowait": 0.00, "irq": 0.00, "soft": 0.00, "steal": 0.00, "guest": 0.00, "gnice": 0.00, "idle": 25.56},
						{"cpu": "12", "usr": 0.00, "nice": 0.00, "sys": 74.03, "iowait": 0.00, "irq": 0.00, "soft": 0.55, "steal": 0.00, "guest": 0.00, "gnice": 0.00, "idle": 25.41},
						{"cpu": "13", "usr": 0.55, "nice": 0.00, "sys": 74.73, "iowait": 0.00, "irq": 0.00, "soft": 0.00, "steal": 0.00, "guest": 0.00, "gnice": 0.00, "idle": 24.73},
						{"cpu": "14", "usr": 0.54, "nice": 0.00, "sys": 75.54, "iowait": 0.00, "irq": 0.00, "soft": 0.54, "steal": 0.00, "guest": 0.00, "gnice": 0.00, "idle": 23.37},
						{"cpu": "15", "usr": 0.54, "nice": 0.00, "sys": 76.22, "iowait": 0.00, "irq": 0.00, "soft": 0.00, "steal": 0.00, "guest": 0.00, "gnice": 0.00, "idle": 23.24}
					]
				},
				{
					"timestamp": "08:50:44 PM",
					"cpu-load": [
						{"cpu": "0", "usr": 0.00, "nice": 0.00, "sys": 0.00, "iowait": 0.00, "irq": 0.00, "soft": 0.00, "steal": 0.00, "guest": 0.00, "gnice": 0.00, "idle": 100.00},
						{"cpu": "1", "usr": 0.00, "nice": 0.00, "sys": 0.00, "iowait": 0.00, "irq": 0.00, "soft": 0.58, "steal": 0.00, "guest": 0.00, "gnice": 0.00, "idle": 99.42},
						{"cpu": "2", "usr": 0.00, "nice": 0.00, "sys": 0.63, "iowait": 0.00, "irq": 0.00, "soft": 1.26, "steal": 0.00, "guest": 0.00, "gnice": 0.00, "idle": 98.11},
						{"cpu": "3", "usr": 0.00, "nice": 0.00, "sys": 0.00, "iowait": 0.00, "irq": 0.00, "soft": 0.00, "steal": 0.00, "guest": 0.00, "gnice": 0.00, "idle": 100.00},
						{"cpu": "4", "usr": 0.00, "nice": 0.00, "sys": 0.59, "iowait": 0.00, "irq": 0.00, "soft": 0.59, "steal": 0.00, "guest": 0.00, "gnice": 0.00, "idle": 98.82},
						{"cpu": "5", "usr": 0.00, "nice": 0.00, "sys": 0.00, "iowait": 0.00, "irq": 0.00, "soft": 0.00, "steal": 0.00, "guest": 0.00, "gnice": 0.00, "idle": 100.00},
						{"cpu": "6", "usr": 0.00, "nice": 0.00, "sys": 0.00, "iowait": 0.00, "irq": 0.00, "soft": 0.00, "steal": 0.00, "guest": 0.00, "gnice": 0.00, "idle": 100.00},
						{"cpu": "7", "usr": 0.00, "nice": 0.00, "sys": 0.57, "iowait": 0.00, "irq": 0.00, "soft": 0.00, "steal": 0.00, "guest": 0.00, "gnice": 0.00, "idle": 99.43},
						{"cpu": "8", "usr": 0.54, "nice": 0.00, "sys": 74.46, "iowait": 0.00, "irq": 0.00, "soft": 0.00, "steal": 0.00, "guest": 0.00, "gnice": 0.00, "idle": 25.00},
						{"cpu": "9", "usr": 0.54, "nice": 0.00, "sys": 73.91, "iowait": 0.00, "irq": 0.00, "soft": 0.00, "steal": 0.00, "guest": 0.00, "gnice": 0.00, "idle": 25.54},
						{"cpu": "10", "usr": 0.00, "nice": 0.00, "sys": 73.48, "iowait": 0.00, "irq": 0.00, "soft": 0.00, "steal": 0.00, "guest": 0.00, "gnice": 0.00, "idle": 26.52},
						{"cpu": "11", "usr": 0.53, "nice": 0.00, "sys": 74.33, "iowait": 0.00, "irq": 0.00, "soft": 0.53, "steal": 0.00, "guest": 0.00, "gnice": 0.00, "idle": 24.60},
						{"cpu": "12", "usr": 0.00, "nice": 0.00, "sys": 72.73, "iowait": 0.00, "irq": 0.00, "soft": 1.07, "steal": 0.00, "guest": 0.00, "gnice": 0.00, "idle": 26.20},
						{"cpu": "13", "usr": 0.54, "nice": 0.00, "sys": 72.43, "iowait": 0.00, "irq": 0.00, "soft": 0.54, "steal": 0.00, "guest": 0.00, "gnice": 0.00, "idle": 26.49},
						{"cpu": "14", "usr": 0.55, "nice": 0.00, "sys": 74.18, "iowait": 0.00, "irq": 0.00, "soft": 0.55, "steal": 0.00, "guest": 0.00, "gnice": 0.00, "idle": 24.73},
						{"cpu": "15", "usr": 0.00, "nice": 0.00, "sys": 73.08, "iowait": 0.00, "irq": 0.00, "soft": 0.00, "steal": 0.00, "guest": 0.00, "gnice": 0.00, "idle": 26.92}
					]
				},
				{
					"timestamp": "08:50:46 PM",
					"cpu-load": [
						{"cpu": "0", "usr": 0.00, "nice": 0.00, "sys": 0.00, "iowait": 0.00, "irq": 0.00, "soft": 0.00, "steal": 0.00, "guest": 0.00, "gnice": 0.00, "idle": 100.00},
						{"cpu": "1", "usr": 0.00, "nice": 0.00, "sys": 0.00, "iowait": 0.00, "irq": 0.00, "soft": 0.58, "steal": 0.00, "guest": 0.00, "gnice": 0.00, "idle": 99.42},
						{"cpu": "2", "usr": 0.00, "nice": 0.00, "sys": 0.00, "iowait": 0.00, "irq": 0.00, "soft": 0.63, "steal": 0.00, "guest": 0.00, "gnice": 0.00, "idle": 99.37},
						{"cpu": "3", "usr": 0.00, "nice": 0.00, "sys": 0.00, "iowait": 0.00, "irq": 0.00, "soft": 0.00, "steal": 0.00, "guest": 0.00, "gnice": 0.00, "idle": 100.00},
						{"cpu": "4", "usr": 0.00, "nice": 0.00, "sys": 0.00, "iowait": 0.00, "irq": 0.00, "soft": 0.59, "steal": 0.00, "guest": 0.00, "gnice": 0.00, "idle": 99.41},
						{"cpu": "5", "usr": 0.00, "nice": 0.00, "sys": 0.00, "iowait": 0.00, "irq": 0.00, "soft": 0.00, "steal": 0.00, "guest": 0.00, "gnice": 0.00, "idle": 100.00},
						{"cpu": "6", "usr": 0.00, "nice": 0.00, "sys": 0.00, "iowait": 0.00, "irq": 0.00, "soft": 0.00, "steal": 0.00, "guest": 0.00, "gnice": 0.00, "idle": 100.00},
						{"cpu": "7", "usr": 0.00, "nice": 0.00, "sys": 0.00, "iowait": 0.00, "irq": 0.00, "soft": 0.57, "steal": 0.00, "guest": 0.00, "gnice": 0.00, "idle": 99.43},
						{"cpu": "8", "usr": 0.54, "nice": 0.00, "sys": 75.54, "iowait": 0.00, "irq": 0.00, "soft": 0.54, "steal": 0.00, "guest": 0.00, "gnice": 0.00, "idle": 23.37},
						{"cpu": "9", "usr": 0.55, "nice": 0.00, "sys": 73.77, "iowait": 0.00, "irq": 0.00, "soft": 0.55, "steal": 0.00, "guest": 0.00, "gnice": 0.00, "idle": 25.14},
						{"cpu": "10", "usr": 0.54, "nice": 0.00, "sys": 74.73, "iowait": 0.00, "irq": 0.00, "soft": 0.54, "steal": 0.00, "guest": 0.00, "gnice": 0.00, "idle": 24.19},
						{"cpu": "11", "usr": 0.00, "nice": 0.00, "sys": 74.59, "iowait": 0.00, "irq": 0.00, "soft": 0.00, "steal": 0.00, "guest": 0.00, "gnice": 0.00, "idle": 25.41},
						{"cpu": "12", "usr": 0.00, "nice": 0.00, "sys": 74.59, "iowait": 0.00, "irq": 0.00, "soft": 0.00, "steal": 0.00, "guest": 0.00, "gnice": 0.00, "idle": 25.41},
						{"cpu": "13", "usr": 0.00, "nice": 0.00, "sys": 74.59, "iowait": 0.00, "irq": 0.00, "soft": 0.54, "steal": 0.00, "guest": 0.00, "gnice": 0.00, "idle": 24.86},
						{"cpu": "14", "usr": 0.00, "nice": 0.00, "sys": 76.11, "iowait": 0.00, "irq": 0.00, "soft": 0.00, "steal": 0.00, "guest": 0.00, "gnice": 0.00, "idle": 23.89},
						{"cpu": "15", "usr": 0.00, "nice": 0.00, "sys": 75.27, "iowait": 0.00, "irq": 0.00, "soft": 0.00, "steal": 0.00, "guest": 0.00, "gnice": 0.00, "idle": 24.73}
					]
				},
				{
					"timestamp": "08:50:48 PM",
					"cpu-load": [
						{"cpu": "0", "usr": 0.00, "nice": 0.00, "sys": 0.00, "iowait": 0.00, "irq": 0.00, "soft": 0.57, "steal": 0.00, "guest": 0.00, "gnice": 0.00, "idle": 99.43},
						{"cpu": "1", "usr": 0.00, "nice": 0.00, "sys": 0.58, "iowait": 0.00, "irq": 0.00, "soft": 0.00, "steal": 0.00, "guest": 0.00, "gnice": 0.00, "idle": 99.42},
						{"cpu": "2", "usr": 0.00, "nice": 0.00, "sys": 0.00, "iowait": 0.00, "irq": 0.00, "soft": 0.62, "steal": 0.00, "guest": 0.00, "gnice": 0.00, "idle": 99.38},
						{"cpu": "3", "usr": 0.00, "nice": 0.00, "sys": 0.52, "iowait": 0.00, "irq": 0.00, "soft": 0.00, "steal": 0.00, "guest": 0.00, "gnice": 0.00, "idle": 99.48},
						{"cpu": "4", "usr": 0.00, "nice": 0.00, "sys": 0.00, "iowait": 0.00, "irq": 0.00, "soft": 0.00, "steal": 0.00, "guest": 0.00, "gnice": 0.00, "idle": 100.00},
						{"cpu": "5", "usr": 0.00, "nice": 0.00, "sys": 0.00, "iowait": 0.00, "irq": 0.00, "soft": 0.00, "steal": 0.00, "guest": 0.00, "gnice": 0.00, "idle": 100.00},
						{"cpu": "6", "usr": 0.00, "nice": 0.00, "sys": 0.00, "iowait": 0.00, "irq": 0.00, "soft": 0.00, "steal": 0.00, "guest": 0.00, "gnice": 0.00, "idle": 100.00},
						{"cpu": "7", "usr": 0.00, "nice": 0.00, "sys": 0.00, "iowait": 0.00, "irq": 0.00, "soft": 0.00, "steal": 0.00, "guest": 0.00, "gnice": 0.00, "idle": 100.00},
						{"cpu": "8", "usr": 0.00, "nice": 0.00, "sys": 75.94, "iowait": 0.00, "irq": 0.00, "soft": 0.53, "steal": 0.00, "guest": 0.00, "gnice": 0.00, "idle": 23.53},
						{"cpu": "9", "usr": 0.00, "nice": 0.00, "sys": 74.59, "iowait": 0.00, "irq": 0.00, "soft": 0.55, "steal": 0.00, "guest": 0.00, "gnice": 0.00, "idle": 24.86},
						{"cpu": "10", "usr": 0.00, "nice": 0.00, "sys": 76.88, "iowait": 0.00, "irq": 0.00, "soft": 0.00, "steal": 0.00, "guest": 0.00, "gnice": 0.00, "idle": 23.12},
						{"cpu": "11", "usr": 0.54, "nice": 0.00, "sys": 75.14, "iowait": 0.00, "irq": 0.00, "soft": 0.00, "steal": 0.00, "guest": 0.00, "gnice": 0.00, "idle": 24.32},
						{"cpu": "12", "usr": 0.53, "nice": 0.00, "sys": 73.40, "iowait": 0.00, "irq": 0.00, "soft": 1.06, "steal": 0.00, "guest": 0.00, "gnice": 0.00, "idle": 25.00},
						{"cpu": "13", "usr": 0.54, "nice": 0.00, "sys": 74.46, "iowait": 0.00, "irq": 0.00, "soft": 0.00, "steal": 0.00, "guest": 0.00, "gnice": 0.00, "idle": 25.00},
						{"cpu": "14", "usr": 0.54, "nice": 0.00, "sys": 75.27, "iowait": 0.00, "irq": 0.00, "soft": 0.54, "steal": 0.00, "guest": 0.00, "gnice": 0.00, "idle": 23.66},
						{"cpu": "15", "usr": 0.55, "nice": 0.00, "sys": 75.27, "iowait": 0.00, "irq": 0.00, "soft": 0.55, "steal": 0.00, "guest": 0.00, "gnice": 0.00, "idle": 23.63}
					]
				},
				{
					"timestamp": "08:50:50 PM",
					"cpu-load": [
						{"cpu": "0", "usr": 0.00, "nice": 0.00, "sys": 0.57, "iowait": 0.00, "irq": 0.00, "soft": 0.57, "steal": 0.00, "guest": 0.00, "gnice": 0.00, "idle": 98.86},
						{"cpu": "1", "usr": 0.00, "nice": 0.00, "sys": 0.00, "iowait": 0.00, "irq": 0.00, "soft": 0.58, "steal": 0.00, "guest": 0.00, "gnice": 0.00, "idle": 99.42},
						{"cpu": "2", "usr": 0.00, "nice": 0.00, "sys": 0.63, "iowait": 0.00, "irq": 0.00, "soft": 0.63, "steal": 0.00, "guest": 0.00, "gnice": 0.00, "idle": 98.74},
						{"cpu": "3", "usr": 0.00, "nice": 0.00, "sys": 0.00, "iowait": 0.00, "irq": 0.00, "soft": 0.00, "steal": 0.00, "guest": 0.00, "gnice": 0.00, "idle": 100.00},
						{"cpu": "4", "usr": 0.00, "nice": 0.00, "sys": 0.00, "iowait": 0.00, "irq": 0.00, "soft": 0.58, "steal": 0.00, "guest": 0.00, "gnice": 0.00, "idle": 99.42},
						{"cpu": "5", "usr": 0.00, "nice": 0.00, "sys": 0.00, "iowait": 0.00, "irq": 0.00, "soft": 0.56, "steal": 0.00, "guest": 0.00, "gnice": 0.00, "idle": 99.44},
						{"cpu": "6", "usr": 0.00, "nice": 0.00, "sys": 0.00, "iowait": 0.00, "irq": 0.00, "soft": 0.00, "steal": 0.00, "guest": 0.00, "gnice": 0.00, "idle": 100.00},
						{"cpu": "7", "usr": 0.00, "nice": 0.00, "sys": 0.58, "iowait": 0.00, "irq": 0.00, "soft": 0.58, "steal": 0.00, "guest": 0.00, "gnice": 0.00, "idle": 98.84},
						{"cpu": "8", "usr": 0.55, "nice": 0.00, "sys": 75.69, "iowait": 0.00, "irq": 0.00, "soft": 0.55, "steal": 0.00, "guest": 0.00, "gnice": 0.00, "idle": 23.20},
						{"cpu": "9", "usr": 0.55, "nice": 0.00, "sys": 74.18, "iowait": 0.00, "irq": 0.00, "soft": 0.55, "steal": 0.00, "guest": 0.00, "gnice": 0.00, "idle": 24.73},
						{"cpu": "10", "usr": 0.00, "nice": 0.00, "sys": 76.63, "iowait": 0.00, "irq": 0.00, "soft": 0.00, "steal": 0.00, "guest": 0.00, "gnice": 0.00, "idle": 23.37},
						{"cpu": "11", "usr": 0.00, "nice": 0.00, "sys": 74.44, "iowait": 0.00, "irq": 0.00, "soft": 0.56, "steal": 0.00, "guest": 0.00, "gnice": 0.00, "idle": 25.00},
						{"cpu": "12", "usr": 0.00, "nice": 0.00, "sys": 74.86, "iowait": 0.00, "irq": 0.00, "soft": 0.55, "steal": 0.00, "guest": 0.00, "gnice": 0.00, "idle": 24.59},
						{"cpu": "13", "usr": 0.54, "nice": 0.00, "sys": 75.27, "iowait": 0.00, "irq": 0.00, "soft": 0.54, "steal": 0.00, "guest": 0.00, "gnice": 0.00, "idle": 23.66},
						{"cpu": "14", "usr": 1.09, "nice": 0.00, "sys": 74.86, "iowait": 0.00, "irq": 0.00, "soft": 0.55, "steal": 0.00, "guest": 0.00, "gnice": 0.00, "idle": 23.50},
						{"cpu": "15", "usr": 0.54, "nice": 0.00, "sys": 76.22, "iowait": 0.00, "irq": 0.00, "soft": 0.00, "steal": 0.00, "guest": 0.00, "gnice": 0.00, "idle": 23.24}
					]
				},
				{
					"timestamp": "08:50:52 PM",
					"cpu-load": [
						{"cpu": "0", "usr": 0.00, "nice": 0.00, "sys": 0.00, "iowait": 0.00, "irq": 0.00, "soft": 0.00, "steal": 0.00, "guest": 0.00, "gnice": 0.00, "idle": 100.00},
						{"cpu": "1", "usr": 0.00, "nice": 0.00, "sys": 0.00, "iowait": 0.00, "irq": 0.00, "soft": 0.00, "steal": 0.00, "guest": 0.00, "gnice": 0.00, "idle": 100.00},
						{"cpu": "2", "usr": 0.00, "nice": 0.00, "sys": 0.00, "iowait": 0.00, "irq": 0.00, "soft": 0.63, "steal": 0.00, "guest": 0.00, "gnice": 0.00, "idle": 99.37},
						{"cpu": "3", "usr": 0.00, "nice": 0.00, "sys": 0.00, "iowait": 0.00, "irq": 0.00, "soft": 0.00, "steal": 0.00, "guest": 0.00, "gnice": 0.00, "idle": 100.00},
						{"cpu": "4", "usr": 0.00, "nice": 0.00, "sys": 0.00, "iowait": 0.00, "irq": 0.00, "soft": 0.59, "steal": 0.00, "guest": 0.00, "gnice": 0.00, "idle": 99.41},
						{"cpu": "5", "usr": 0.00, "nice": 0.00, "sys": 0.56, "iowait": 0.00, "irq": 0.00, "soft": 0.00, "steal": 0.00, "guest": 0.00, "gnice": 0.00, "idle": 99.44},
						{"cpu": "6", "usr": 0.00, "nice": 0.00, "sys": 0.00, "iowait": 0.00, "irq": 0.00, "soft": 0.00, "steal": 0.00, "guest": 0.00, "gnice": 0.00, "idle": 100.00},
						{"cpu": "7", "usr": 0.00, "nice": 0.00, "sys": 0.00, "iowait": 0.00, "irq": 0.00, "soft": 0.58, "steal": 0.00, "guest": 0.00, "gnice": 0.00, "idle": 99.42},
						{"cpu": "8", "usr": 0.00, "nice": 0.00, "sys": 76.22, "iowait": 0.00, "irq": 0.00, "soft": 0.00, "steal": 0.00, "guest": 0.00, "gnice": 0.00, "idle": 23.78},
						{"cpu": "9", "usr": 0.53, "nice": 0.00, "sys": 74.87, "iowait": 0.00, "irq": 0.00, "soft": 0.00, "steal": 0.00, "guest": 0.00, "gnice": 0.00, "idle": 24.60},
						{"cpu": "10", "usr": 0.54, "nice": 0.00, "sys": 75.14, "iowait": 0.00, "irq": 0.00, "soft": 0.00, "steal": 0.00, "guest": 0.00, "gnice": 0.00, "idle": 24.32},
						{"cpu": "11", "usr": 0.54, "nice": 0.00, "sys": 74.46, "iowait": 0.00, "irq": 0.00, "soft": 0.54, "steal": 0.00, "guest": 0.00, "gnice": 0.00, "idle": 24.46},
						{"cpu": "12", "usr": 0.00, "nice": 0.00, "sys": 74.18, "iowait": 0.00, "irq": 0.00, "soft": 0.55, "steal": 0.00, "guest": 0.00, "gnice": 0.00, "idle": 25.27},
						{"cpu": "13", "usr": 0.54, "nice": 0.00, "sys": 75.54, "iowait": 0.00, "irq": 0.00, "soft": 0.00, "steal": 0.00, "guest": 0.00, "gnice": 0.00, "idle": 23.91},
						{"cpu": "14", "usr": 0.00, "nice": 0.00, "sys": 75.96, "iowait": 0.00, "irq": 0.00, "soft": 0.00, "steal": 0.00, "guest": 0.00, "gnice": 0.00, "idle": 24.04},
						{"cpu": "15", "usr": 0.53, "nice": 0.00, "sys": 75.00, "iowait": 0.00, "irq": 0.00, "soft": 0.53, "steal": 0.00, "guest": 0.00, "gnice": 0.00, "idle": 23.94}
					]
				},
				{
					"timestamp": "08:50:54 PM",
					"cpu-load": [
						{"cpu": "0", "usr": 0.00, "nice": 0.00, "sys": 0.00, "iowait": 0.00, "irq": 0.00, "soft": 0.58, "steal": 0.00, "guest": 0.00, "gnice": 0.00, "idle": 99.42},
						{"cpu": "1", "usr": 0.00, "nice": 0.00, "sys": 0.00, "iowait": 0.00, "irq": 0.00, "soft": 0.57, "steal": 0.00, "guest": 0.00, "gnice": 0.00, "idle": 99.43},
						{"cpu": "2", "usr": 0.00, "nice": 0.00, "sys": 0.00, "iowait": 0.00, "irq": 0.00, "soft": 0.63, "steal": 0.00, "guest": 0.00, "gnice": 0.00, "idle": 99.37},
						{"cpu": "3", "usr": 0.00, "nice": 0.00, "sys": 0.52, "iowait": 0.00, "irq": 0.00, "soft": 0.00, "steal": 0.00, "guest": 0.00, "gnice": 0.00, "idle": 99.48},
						{"cpu": "4", "usr": 0.00, "nice": 0.00, "sys": 0.00, "iowait": 0.00, "irq": 0.00, "soft": 0.00, "steal": 0.00, "guest": 0.00, "gnice": 0.00, "idle": 100.00},
						{"cpu": "5", "usr": 0.00, "nice": 0.00, "sys": 0.00, "iowait": 0.00, "irq": 0.00, "soft": 0.57, "steal": 0.00, "guest": 0.00, "gnice": 0.00, "idle": 99.43},
						{"cpu": "6", "usr": 0.00, "nice": 0.00, "sys": 0.00, "iowait": 0.00, "irq": 0.00, "soft": 0.52, "steal": 0.00, "guest": 0.00, "gnice": 0.00, "idle": 99.48},
						{"cpu": "7", "usr": 0.00, "nice": 0.00, "sys": 0.00, "iowait": 0.00, "irq": 0.00, "soft": 0.57, "steal": 0.00, "guest": 0.00, "gnice": 0.00, "idle": 99.43},
						{"cpu": "8", "usr": 0.54, "nice": 0.00, "sys": 76.09, "iowait": 0.00, "irq": 0.00, "soft": 0.00, "steal": 0.00, "guest": 0.00, "gnice": 0.00, "idle": 23.37},
						{"cpu": "9", "usr": 0.00, "nice": 0.00, "sys": 75.92, "iowait": 0.00, "irq": 0.00, "soft": 0.52, "steal": 0.00, "guest": 0.00, "gnice": 0.00, "idle": 23.56},
						{"cpu": "10", "usr": 0.00, "nice": 0.00, "sys": 75.14, "iowait": 0.00, "irq": 0.00, "soft": 0.54, "steal": 0.00, "guest": 0.00, "gnice": 0.00, "idle": 24.32},
						{"cpu": "11", "usr": 0.00, "nice": 0.00, "sys": 76.06, "iowait": 0.00, "irq": 0.00, "soft": 0.53, "steal": 0.00, "guest": 0.00, "gnice": 0.00, "idle": 23.40},
						{"cpu": "12", "usr": 0.54, "nice": 0.00, "sys": 73.91, "iowait": 0.00, "irq": 0.00, "soft": 0.54, "steal": 0.00, "guest": 0.00, "gnice": 0.00, "idle": 25.00},
						{"cpu": "13", "usr": 0.00, "nice": 0.00, "sys": 75.81, "iowait": 0.00, "irq": 0.00, "soft": 0.54, "steal": 0.00, "guest": 0.00, "gnice": 0.00, "idle": 23.66},
						{"cpu": "14", "usr": 0.54, "nice": 0.00, "sys": 75.81, "iowait": 0.00, "irq": 0.00, "soft": 0.00, "steal": 0.00, "guest": 0.00, "gnice": 0.00, "idle": 23.66},
						{"cpu": "15", "usr": 0.00, "nice": 0.00, "sys": 76.34, "iowait": 0.00, "irq": 0.00, "soft": 0.00, "steal": 0.00, "guest": 0.00, "gnice": 0.00, "idle": 23.66}
					]
				},
				{
					"timestamp": "08:50:56 PM",
					"cpu-load": [
						{"cpu": "0", "usr": 0.00, "nice": 0.00, "sys": 0.00, "iowait": 0.00, "irq": 0.00, "soft": 0.00, "steal": 0.00, "guest": 0.00, "gnice": 0.00, "idle": 100.00},
						{"cpu": "1", "usr": 0.00, "nice": 0.00, "sys": 0.00, "iowait": 0.00, "irq": 0.00, "soft": 0.00, "steal": 0.00, "guest": 0.00, "gnice": 0.00, "idle": 100.00},
						{"cpu": "2", "usr": 0.00, "nice": 0.00, "sys": 0.00, "iowait": 0.00, "irq": 0.00, "soft": 0.63, "steal": 0.00, "guest": 0.00, "gnice": 0.00, "idle": 99.37},
						{"cpu": "3", "usr": 0.00, "nice": 0.00, "sys": 0.52, "iowait": 0.00, "irq": 0.00, "soft": 0.52, "steal": 0.00, "guest": 0.00, "gnice": 0.00, "idle": 98.96},
						{"cpu": "4", "usr": 0.00, "nice": 0.00, "sys": 0.00, "iowait": 0.00, "irq": 0.00, "soft": 0.59, "steal": 0.00, "guest": 0.00, "gnice": 0.00, "idle": 99.41},
						{"cpu": "5", "usr": 0.00, "nice": 0.00, "sys": 0.00, "iowait": 0.00, "irq": 0.00, "soft": 0.57, "steal": 0.00, "guest": 0.00, "gnice": 0.00, "idle": 99.43},
						{"cpu": "6", "usr": 0.00, "nice": 0.00, "sys": 0.00, "iowait": 0.00, "irq": 0.00, "soft": 0.00, "steal": 0.00, "guest": 0.00, "gnice": 0.00, "idle": 100.00},
						{"cpu": "7", "usr": 0.00, "nice": 0.00, "sys": 0.00, "iowait": 0.00, "irq": 0.00, "soft": 0.00, "steal": 0.00, "guest": 0.00, "gnice": 0.00, "idle": 100.00},
						{"cpu": "8", "usr": 0.54, "nice": 0.00, "sys": 75.27, "iowait": 0.00, "irq": 0.00, "soft": 0.54, "steal": 0.00, "guest": 0.00, "gnice": 0.00, "idle": 23.66},
						{"cpu": "9", "usr": 0.55, "nice": 0.00, "sys": 74.18, "iowait": 0.00, "irq": 0.00, "soft": 0.55, "steal": 0.00, "guest": 0.00, "gnice": 0.00, "idle": 24.73},
						{"cpu": "10", "usr": 0.54, "nice": 0.00, "sys": 74.59, "iowait": 0.00, "irq": 0.00, "soft": 0.54, "steal": 0.00, "guest": 0.00, "gnice": 0.00, "idle": 24.32},
						{"cpu": "11", "usr": 0.55, "nice": 0.00, "sys": 75.82, "iowait": 0.00, "irq": 0.00, "soft": 0.00, "steal": 0.00, "guest": 0.00, "gnice": 0.00, "idle": 23.63},
						{"cpu": "12", "usr": 0.55, "nice": 0.00, "sys": 74.59, "iowait": 0.00, "irq": 0.00, "soft": 0.55, "steal": 0.00, "guest": 0.00, "gnice": 0.00, "idle": 24.31},
						{"cpu": "13", "usr": 0.54, "nice": 0.00, "sys": 75.81, "iowait": 0.00, "irq": 0.00, "soft": 0.00, "steal": 0.00, "guest": 0.00, "gnice": 0.00, "idle": 23.66},
						{"cpu": "14", "usr": 0.00, "nice": 0.00, "sys": 75.54, "iowait": 0.00, "irq": 0.00, "soft": 0.54, "steal": 0.00, "guest": 0.00, "gnice": 0.00, "idle": 23.91},
						{"cpu": "15", "usr": 0.54, "nice": 0.00, "sys": 74.05, "iowait": 0.00, "irq": 0.00, "soft": 0.54, "steal": 0.00, "guest": 0.00, "gnice": 0.00, "idle": 24.86}
					]
				},
				{
					"timestamp": "08:50:58 PM",
					"cpu-load": [
						{"cpu": "0", "usr": 0.00, "nice": 0.00, "sys": 0.57, "iowait": 0.00, "irq": 0.00, "soft": 0.57, "steal": 0.00, "guest": 0.00, "gnice": 0.00, "idle": 98.86},
						{"cpu": "1", "usr": 0.00, "nice": 0.00, "sys": 0.00, "iowait": 0.00, "irq": 0.00, "soft": 0.00, "steal": 0.00, "guest": 0.00, "gnice": 0.00, "idle": 100.00},
						{"cpu": "2", "usr": 0.00, "nice": 0.00, "sys": 0.00, "iowait": 0.00, "irq": 0.00, "soft": 0.63, "steal": 0.00, "guest": 0.00, "gnice": 0.00, "idle": 99.37},
						{"cpu": "3", "usr": 0.00, "nice": 0.00, "sys": 0.00, "iowait": 0.00, "irq": 0.00, "soft": 0.00, "steal": 0.00, "guest": 0.00, "gnice": 0.00, "idle": 100.00},
						{"cpu": "4", "usr": 0.00, "nice": 0.00, "sys": 0.00, "iowait": 0.00, "irq": 0.00, "soft": 0.59, "steal": 0.00, "guest": 0.00, "gnice": 0.00, "idle": 99.41},
						{"cpu": "5", "usr": 0.00, "nice": 0.00, "sys": 0.57, "iowait": 0.00, "irq": 0.00, "soft": 0.00, "steal": 0.00, "guest": 0.00, "gnice": 0.00, "idle": 99.43},
						{"cpu": "6", "usr": 0.00, "nice": 0.00, "sys": 0.00, "iowait": 0.00, "irq": 0.00, "soft": 0.00, "steal": 0.00, "guest": 0.00, "gnice": 0.00, "idle": 100.00},
						{"cpu": "7", "usr": 0.00, "nice": 0.00, "sys": 0.56, "iowait": 0.00, "irq": 0.00, "soft": 0.56, "steal": 0.00, "guest": 0.00, "gnice": 0.00, "idle": 98.87},
						{"cpu": "8", "usr": 0.00, "nice": 0.00, "sys": 76.50, "iowait": 0.00, "irq": 0.00, "soft": 0.00, "steal": 0.00, "guest": 0.00, "gnice": 0.00, "idle": 23.50},
						{"cpu": "9", "usr": 0.00, "nice": 0.00, "sys": 74.43, "iowait": 0.00, "irq": 0.00, "soft": 0.00, "steal": 0.00, "guest": 0.00, "gnice": 0.00, "idle": 25.57},
						{"cpu": "10", "usr": 0.00, "nice": 0.00, "sys": 75.41, "iowait": 0.00, "irq": 0.00, "soft": 0.00, "steal": 0.00, "guest": 0.00, "gnice": 0.00, "idle": 24.59},
						{"cpu": "11", "usr": 0.54, "nice": 0.00, "sys": 75.54, "iowait": 0.00, "irq": 0.00, "soft": 0.54, "steal": 0.00, "guest": 0.00, "gnice": 0.00, "idle": 23.37},
						{"cpu": "12", "usr": 0.53, "nice": 0.00, "sys": 73.94, "iowait": 0.00, "irq": 0.00, "soft": 1.06, "steal": 0.00, "guest": 0.00, "gnice": 0.00, "idle": 24.47},
						{"cpu": "13", "usr": 0.54, "nice": 0.00, "sys": 75.68, "iowait": 0.00, "irq": 0.00, "soft": 0.54, "steal": 0.00, "guest": 0.00, "gnice": 0.00, "idle": 23.24},
						{"cpu": "14", "usr": 0.53, "nice": 0.00, "sys": 75.94, "iowait": 0.00, "irq": 0.00, "soft": 0.53, "steal": 0.00, "guest": 0.00, "gnice": 0.00, "idle": 22.99},
						{"cpu": "15", "usr": 0.54, "nice": 0.00, "sys": 74.73, "iowait": 0.00, "irq": 0.00, "soft": 0.54, "steal": 0.00, "guest": 0.00, "gnice": 0.00, "idle": 24.19}
					]
				},
				{
					"timestamp": "08:51:00 PM",
					"cpu-load": [
						{"cpu": "0", "usr": 0.00, "nice": 0.00, "sys": 0.00, "iowait": 0.00, "irq": 0.00, "soft": 0.00, "steal": 0.00, "guest": 0.00, "gnice": 0.00, "idle": 100.00},
						{"cpu": "1", "usr": 0.00, "nice": 0.00, "sys": 0.00, "iowait": 0.00, "irq": 0.00, "soft": 0.57, "steal": 0.00, "guest": 0.00, "gnice": 0.00, "idle": 99.43},
						{"cpu": "2", "usr": 0.00, "nice": 0.00, "sys": 0.00, "iowait": 0.00, "irq": 0.00, "soft": 0.62, "steal": 0.00, "guest": 0.00, "gnice": 0.00, "idle": 99.38},
						{"cpu": "3", "usr": 0.00, "nice": 0.00, "sys": 0.00, "iowait": 0.00, "irq": 0.00, "soft": 0.00, "steal": 0.00, "guest": 0.00, "gnice": 0.00, "idle": 100.00},
						{"cpu": "4", "usr": 0.00, "nice": 0.00, "sys": 0.58, "iowait": 0.00, "irq": 0.00, "soft": 0.00, "steal": 0.00, "guest": 0.00, "gnice": 0.00, "idle": 99.42},
						{"cpu": "5", "usr": 0.00, "nice": 0.00, "sys": 0.00, "iowait": 0.00, "irq": 0.00, "soft": 0.56, "steal": 0.00, "guest": 0.00, "gnice": 0.00, "idle": 99.44},
						{"cpu": "6", "usr": 0.00, "nice": 0.00, "sys": 0.00, "iowait": 0.00, "irq": 0.00, "soft": 0.00, "steal": 0.00, "guest": 0.00, "gnice": 0.00, "idle": 100.00},
						{"cpu": "7", "usr": 0.00, "nice": 0.00, "sys": 0.00, "iowait": 0.00, "irq": 0.00, "soft": 0.00, "steal": 0.00, "guest": 0.00, "gnice": 0.00, "idle": 100.00},
						{"cpu": "8", "usr": 0.54, "nice": 0.00, "sys": 75.54, "iowait": 0.00, "irq": 0.00, "soft": 0.54, "steal": 0.00, "guest": 0.00, "gnice": 0.00, "idle": 23.37},
						{"cpu": "9", "usr": 0.56, "nice": 0.00, "sys": 74.44, "iowait": 0.00, "irq": 0.00, "soft": 0.00, "steal": 0.00, "guest": 0.00, "gnice": 0.00, "idle": 25.00},
						{"cpu": "10", "usr": 0.00, "nice": 0.00, "sys": 75.00, "iowait": 0.00, "irq": 0.00, "soft": 0.56, "steal": 0.00, "guest": 0.00, "gnice": 0.00, "idle": 24.44},
						{"cpu": "11", "usr": 0.56, "nice": 0.00, "sys": 75.56, "iowait": 0.00, "irq": 0.00, "soft": 0.00, "steal": 0.00, "guest": 0.00, "gnice": 0.00, "idle": 23.89},
						{"cpu": "12", "usr": 0.00, "nice": 0.00, "sys": 75.00, "iowait": 0.00, "irq": 0.00, "soft": 0.56, "steal": 0.00, "guest": 0.00, "gnice": 0.00, "idle": 24.44},
						{"cpu": "13", "usr": 0.54, "nice": 0.00, "sys": 76.09, "iowait": 0.00, "irq": 0.00, "soft": 0.00, "steal": 0.00, "guest": 0.00, "gnice": 0.00, "idle": 23.37},
						{"cpu": "14", "usr": 0.00, "nice": 0.00, "sys": 75.56, "iowait": 0.00, "irq": 0.00, "soft": 0.56, "steal": 0.00, "guest": 0.00, "gnice": 0.00, "idle": 23.89},
						{"cpu": "15", "usr": 0.00, "nice": 0.00, "sys": 75.41, "iowait": 0.00, "irq": 0.00, "soft": 0.00, "steal": 0.00, "guest": 0.00, "gnice": 0.00, "idle": 24.59}
					]
				},
				{
					"timestamp": "08:51:02 PM",
					"cpu-load": [
						{"cpu": "0", "usr": 0.00, "nice": 0.00, "sys": 0.58, "iowait": 0.00, "irq": 0.00, "soft": 0.58, "steal": 0.00, "guest": 0.00, "gnice": 0.00, "idle": 98.83},
						{"cpu": "1", "usr": 0.00, "nice": 0.00, "sys": 0.00, "iowait": 0.00, "irq": 0.00, "soft": 0.57, "steal": 0.00, "guest": 0.00, "gnice": 0.00, "idle": 99.43},
						{"cpu": "2", "usr": 0.00, "nice": 0.00, "sys": 0.00, "iowait": 0.00, "irq": 0.00, "soft": 0.63, "steal": 0.00, "guest": 0.00, "gnice": 0.00, "idle": 99.37},
						{"cpu": "3", "usr": 0.00, "nice": 0.00, "sys": 0.00, "iowait": 0.00, "irq": 0.00, "soft": 0.00, "steal": 0.00, "guest": 0.00, "gnice": 0.00, "idle": 100.00},
						{"cpu": "4", "usr": 0.00, "nice": 0.00, "sys": 0.00, "iowait": 0.00, "irq": 0.00, "soft": 0.59, "steal": 0.00, "guest": 0.00, "gnice": 0.00, "idle": 99.41},
						{"cpu": "5", "usr": 0.00, "nice": 0.00, "sys": 0.00, "iowait": 0.00, "irq": 0.00, "soft": 0.57, "steal": 0.00, "guest": 0.00, "gnice": 0.00, "idle": 99.43},
						{"cpu": "6", "usr": 0.00, "nice": 0.00, "sys": 0.00, "iowait": 0.00, "irq": 0.00, "soft": 0.00, "steal": 0.00, "guest": 0.00, "gnice": 0.00, "idle": 100.00},
						{"cpu": "7", "usr": 0.00, "nice": 0.00, "sys": 0.00, "iowait": 0.00, "irq": 0.00, "soft": 0.56, "steal": 0.00, "guest": 0.00, "gnice": 0.00, "idle": 99.44},
						{"cpu": "8", "usr": 0.00, "nice": 0.00, "sys": 75.96, "iowait": 0.00, "irq": 0.00, "soft": 0.55, "steal": 0.00, "guest": 0.00, "gnice": 0.00, "idle": 23.50},
						{"cpu": "9", "usr": 0.00, "nice": 0.00, "sys": 74.86, "iowait": 0.00, "irq": 0.00, "soft": 0.55, "steal": 0.00, "guest": 0.00, "gnice": 0.00, "idle": 24.59},
						{"cpu": "10", "usr": 0.55, "nice": 0.00, "sys": 74.86, "iowait": 0.00, "irq": 0.00, "soft": 0.00, "steal": 0.00, "guest": 0.00, "gnice": 0.00, "idle": 24.59},
						{"cpu": "11", "usr": 0.54, "nice": 0.00, "sys": 75.54, "iowait": 0.00, "irq": 0.00, "soft": 0.54, "steal": 0.00, "guest": 0.00, "gnice": 0.00, "idle": 23.37},
						{"cpu": "12", "usr": 0.54, "nice": 0.00, "sys": 75.00, "iowait": 0.00, "irq": 0.00, "soft": 0.54, "steal": 0.00, "guest": 0.00, "gnice": 0.00, "idle": 23.91},
						{"cpu": "13", "usr": 0.00, "nice": 0.00, "sys": 76.50, "iowait": 0.00, "irq": 0.00, "soft": 0.00, "steal": 0.00, "guest": 0.00, "gnice": 0.00, "idle": 23.50},
						{"cpu": "14", "usr": 0.56, "nice": 0.00, "sys": 74.44, "iowait": 0.00, "irq": 0.00, "soft": 0.56, "steal": 0.00, "guest": 0.00, "gnice": 0.00, "idle": 24.44},
						{"cpu": "15", "usr": 0.53, "nice": 0.00, "sys": 74.87, "iowait": 0.00, "irq": 0.00, "soft": 0.53, "steal": 0.00, "guest": 0.00, "gnice": 0.00, "idle": 24.06}
					]
				},
				{
					"timestamp": "08:51:04 PM",
					"cpu-load": [
						{"cpu": "0", "usr": 0.00, "nice": 0.00, "sys": 0.00, "iowait": 0.00, "irq": 0.00, "soft": 0.58, "steal": 0.00, "guest": 0.00, "gnice": 0.00, "idle": 99.42},
						{"cpu": "1", "usr": 0.00, "nice": 0.00, "sys": 0.58, "iowait": 0.00, "irq": 0.00, "soft": 0.00, "steal": 0.00, "guest": 0.00, "gnice": 0.00, "idle": 99.42},
						{"cpu": "2", "usr": 0.00, "nice": 0.00, "sys": 0.63, "iowait": 0.00, "irq": 0.00, "soft": 0.00, "steal": 0.00, "guest": 0.00, "gnice": 0.00, "idle": 99.37},
						{"cpu": "3", "usr": 0.00, "nice": 0.00, "sys": 0.52, "iowait": 0.00, "irq": 0.00, "soft": 0.00, "steal": 0.00, "guest": 0.00, "gnice": 0.00, "idle": 99.48},
						{"cpu": "4", "usr": 0.00, "nice": 0.00, "sys": 0.00, "iowait": 0.00, "irq": 0.00, "soft": 0.59, "steal": 0.00, "guest": 0.00, "gnice": 0.00, "idle": 99.41},
						{"cpu": "5", "usr": 0.00, "nice": 0.00, "sys": 0.00, "iowait": 0.00, "irq": 0.00, "soft": 0.00, "steal": 0.00, "guest": 0.00, "gnice": 0.00, "idle": 100.00},
						{"cpu": "6", "usr": 0.00, "nice": 0.00, "sys": 0.00, "iowait": 0.00, "irq": 0.00, "soft": 0.00, "steal": 0.00, "guest": 0.00, "gnice": 0.00, "idle": 100.00},
						{"cpu": "7", "usr": 0.00, "nice": 0.00, "sys": 0.00, "iowait": 0.00, "irq": 0.00, "soft": 0.57, "steal": 0.00, "guest": 0.00, "gnice": 0.00, "idle": 99.43},
						{"cpu": "8", "usr": 0.54, "nice": 0.00, "sys": 76.34, "iowait": 0.00, "irq": 0.00, "soft": 0.00, "steal": 0.00, "guest": 0.00, "gnice": 0.00, "idle": 23.12},
						{"cpu": "9", "usr": 0.53, "nice": 0.00, "sys": 75.66, "iowait": 0.00, "irq": 0.00, "soft": 0.53, "steal": 0.00, "guest": 0.00, "gnice": 0.00, "idle": 23.28},
						{"cpu": "10", "usr": 0.55, "nice": 0.00, "sys": 74.86, "iowait": 0.00, "irq": 0.00, "soft": 0.00, "steal": 0.00, "guest": 0.00, "gnice": 0.00, "idle": 24.59},
						{"cpu": "11", "usr": 0.00, "nice": 0.00, "sys": 75.82, "iowait": 0.00, "irq": 0.00, "soft": 0.00, "steal": 0.00, "guest": 0.00, "gnice": 0.00, "idle": 24.18},
						{"cpu": "12", "usr": 0.54, "nice": 0.00, "sys": 75.14, "iowait": 0.00, "irq": 0.00, "soft": 0.54, "steal": 0.00, "guest": 0.00, "gnice": 0.00, "idle": 23.78},
						{"cpu": "13", "usr": 0.53, "nice": 0.00, "sys": 75.94, "iowait": 0.00, "irq": 0.00, "soft": 0.00, "steal": 0.00, "guest": 0.00, "gnice": 0.00, "idle": 23.53},
						{"cpu": "14", "usr": 0.53, "nice": 0.00, "sys": 75.94, "iowait": 0.00, "irq": 0.00, "soft": 0.53, "steal": 0.00, "guest": 0.00, "gnice": 0.00, "idle": 22.99},
						{"cpu": "15", "usr": 0.55, "nice": 0.00, "sys": 74.59, "iowait": 0.00, "irq": 0.00, "soft": 0.00, "steal": 0.00, "guest": 0.00, "gnice": 0.00, "idle": 24.86}
					]
				}
			]
		}
	]
}}
